{"data":{"zipFile":{"publicURL":"/roadbike/static/2018-10-10 正文标题编号-c1e73d627466c8b0dcb5bc7a66e22286.zip"},"pdfFile":{"publicURL":"/roadbike/static/2018-10-10 正文标题编号-39f6c51dcee3abe36fbc581263322ffa.pdf"},"site":{"siteMetadata":{"title":"小书匠","siteUrl":"http://www.xiaoshujiang.com"}},"storyWriterMarkdown":{"id":"db04f63c-f588-54b9-bf0c-5ac7b5b5783c","html":"\n\n\t<div class=\"preview html_preview xsj_export_zip\"><div style=\"overflow: hidden; position: absolute; top: 0px; height: 1px; width: auto; padding: 0px; border: 0px; margin: 0px; text-align: left; text-indent: 0px; text-transform: none; line-height: normal; letter-spacing: normal; word-spacing: normal; display: none;\"><svg style=\"display: none;\"><defs id=\"MathJax_SVG_glyphs\"/></svg></div><p class=\"xsj_paragraph xsj_paragraph_level_0\"></p><div class=\"toc mindmap_toc mindmap_container\" data-info=\"direction=lr&amp;root=章节标题编号\" data-hash=\"675458d875f19ed8405656d301a644f7_mindmap_toc\"><div class=\"xsj_mindmap xsj_mindmap_toc\"><svg id=\"xsj_mindmap_toc_1547637043961\" xmlns=\"http://www.w3.org/2000/svg\" xmlns:xlink=\"http://www.w3.org/1999/xlink\" version=\"1.1\" class=\"xsj_svg_viewbox\" style=\"max-width:970px;max-height:616px;\" viewbox=\"0 0 970 616\" width=\"100%\" height=\"100%\"><g transform=\"translate(198,294.75) scale(1)\"><g class=\"markmap-link\" style=\"fill:none;\"><path stroke=\"#98df8a\" stroke-width=\"6\" d=\"M118,-258.75 L123,-258.75 C159,-258.75 154,-258.75 190,-258.75 L192,-258.75\"/><polygon class=\"markmap-link-polygon\" stroke-width=\"0\" transform=\"translate(118, -258.75)\" points=\"0,-3 5,0 0,3 -5,0\" style=\"fill: white;\"/></g><g class=\"markmap-link\" style=\"fill:none;\"><path stroke=\"#2ca02c\" stroke-width=\"6\" d=\"M330,-143.75 L335,-143.75 C371,-143.75 366,-120.75 402,-120.75 L404,-120.75\"/><polygon class=\"markmap-link-polygon\" stroke-width=\"0\" transform=\"translate(330, -143.75)\" points=\"0,-3 5,0 0,3 -5,0\" style=\"fill: white;\"/></g><g class=\"markmap-link\" style=\"fill:none;\"><path stroke=\"#2ca02c\" stroke-width=\"6\" d=\"M330,-143.75 L335,-143.75 C371,-143.75 366,-166.75 402,-166.75 L404,-166.75\"/><polygon class=\"markmap-link-polygon\" stroke-width=\"0\" transform=\"translate(330, -143.75)\" points=\"0,-3 5,0 0,3 -5,0\" style=\"fill: white;\"/></g><g class=\"markmap-link\" style=\"fill:none;\"><path stroke=\"#2ca02c\" stroke-width=\"6\" d=\"M216,-178.25 L221,-178.25 C257,-178.25 252,-143.75 288,-143.75 L290,-143.75\"/><polygon class=\"markmap-link-polygon\" stroke-width=\"0\" transform=\"translate(216, -178.25)\" points=\"0,-3 5,0 0,3 -5,0\" style=\"fill: white;\"/></g><g class=\"markmap-link\" style=\"fill:none;\"><path stroke=\"#2ca02c\" stroke-width=\"6\" d=\"M216,-178.25 L221,-178.25 C257,-178.25 252,-212.75 288,-212.75 L290,-212.75\"/><polygon class=\"markmap-link-polygon\" stroke-width=\"0\" transform=\"translate(216, -178.25)\" points=\"0,-3 5,0 0,3 -5,0\" style=\"fill: white;\"/></g><g class=\"markmap-link\" style=\"fill:none;\"><path stroke=\"#ffbb78\" stroke-width=\"6\" d=\"M330,-5.75 L335,-5.75 C371,-5.75 366,17.25 402,17.25 L404,17.25\"/><polygon class=\"markmap-link-polygon\" stroke-width=\"0\" transform=\"translate(330, -5.75)\" points=\"0,-3 5,0 0,3 -5,0\" style=\"fill: white;\"/></g><g class=\"markmap-link\" style=\"fill:none;\"><path stroke=\"#ffbb78\" stroke-width=\"6\" d=\"M330,-5.75 L335,-5.75 C371,-5.75 366,-28.75 402,-28.75 L404,-28.75\"/><polygon class=\"markmap-link-polygon\" stroke-width=\"0\" transform=\"translate(330, -5.75)\" points=\"0,-3 5,0 0,3 -5,0\" style=\"fill: white;\"/></g><g class=\"markmap-link\" style=\"fill:none;\"><path stroke=\"#ffbb78\" stroke-width=\"6\" d=\"M216,-40.25 L221,-40.25 C257,-40.25 252,-5.75 288,-5.75 L290,-5.75\"/><polygon class=\"markmap-link-polygon\" stroke-width=\"0\" transform=\"translate(216, -40.25)\" points=\"0,-3 5,0 0,3 -5,0\" style=\"fill: white;\"/></g><g class=\"markmap-link\" style=\"fill:none;\"><path stroke=\"#ffbb78\" stroke-width=\"6\" d=\"M216,-40.25 L221,-40.25 C257,-40.25 252,-74.75 288,-74.75 L290,-74.75\"/><polygon class=\"markmap-link-polygon\" stroke-width=\"0\" transform=\"translate(216, -40.25)\" points=\"0,-3 5,0 0,3 -5,0\" style=\"fill: white;\"/></g><g class=\"markmap-link\" style=\"fill:none;\"><path stroke=\"#ff7f0e\" stroke-width=\"6\" d=\"M556,109.25 L561,109.25 C597,109.25 592,109.25 628,109.25 L630,109.25\"/><polygon class=\"markmap-link-polygon\" stroke-width=\"0\" transform=\"translate(556, 109.25)\" points=\"0,-3 5,0 0,3 -5,0\" style=\"fill: white;\"/></g><g class=\"markmap-link\" style=\"fill:none;\"><path stroke=\"#ff7f0e\" stroke-width=\"6\" d=\"M344,155.25 L349,155.25 C385,155.25 380,201.25 416,201.25 L418,201.25\"/><polygon class=\"markmap-link-polygon\" stroke-width=\"0\" transform=\"translate(344, 155.25)\" points=\"0,-3 5,0 0,3 -5,0\" style=\"fill: white;\"/></g><g class=\"markmap-link\" style=\"fill:none;\"><path stroke=\"#ff7f0e\" stroke-width=\"6\" d=\"M344,155.25 L349,155.25 C385,155.25 380,155.25 416,155.25 L418,155.25\"/><polygon class=\"markmap-link-polygon\" stroke-width=\"0\" transform=\"translate(344, 155.25)\" points=\"0,-3 5,0 0,3 -5,0\" style=\"fill: white;\"/></g><g class=\"markmap-link\" style=\"fill:none;\"><path stroke=\"#ff7f0e\" stroke-width=\"6\" d=\"M344,155.25 L349,155.25 C385,155.25 380,109.25 416,109.25 L418,109.25\"/><polygon class=\"markmap-link-polygon\" stroke-width=\"0\" transform=\"translate(344, 155.25)\" points=\"0,-3 5,0 0,3 -5,0\" style=\"fill: white;\"/></g><g class=\"markmap-link\" style=\"fill:none;\"><path stroke=\"#ff7f0e\" stroke-width=\"6\" d=\"M330,270.25 L335,270.25 C371,270.25 366,293.25 402,293.25 L404,293.25\"/><polygon class=\"markmap-link-polygon\" stroke-width=\"0\" transform=\"translate(330, 270.25)\" points=\"0,-3 5,0 0,3 -5,0\" style=\"fill: white;\"/></g><g class=\"markmap-link\" style=\"fill:none;\"><path stroke=\"#ff7f0e\" stroke-width=\"6\" d=\"M330,270.25 L335,270.25 C371,270.25 366,247.25 402,247.25 L404,247.25\"/><polygon class=\"markmap-link-polygon\" stroke-width=\"0\" transform=\"translate(330, 270.25)\" points=\"0,-3 5,0 0,3 -5,0\" style=\"fill: white;\"/></g><g class=\"markmap-link\" style=\"fill:none;\"><path stroke=\"#ff7f0e\" stroke-width=\"6\" d=\"M216,166.75 L221,166.75 C257,166.75 252,270.25 288,270.25 L290,270.25\"/><polygon class=\"markmap-link-polygon\" stroke-width=\"0\" transform=\"translate(216, 166.75)\" points=\"0,-3 5,0 0,3 -5,0\" style=\"fill: white;\"/></g><g class=\"markmap-link\" style=\"fill:none;\"><path stroke=\"#ff7f0e\" stroke-width=\"6\" d=\"M216,166.75 L221,166.75 C257,166.75 252,155.25 288,155.25 L290,155.25\"/><polygon class=\"markmap-link-polygon\" stroke-width=\"0\" transform=\"translate(216, 166.75)\" points=\"0,-3 5,0 0,3 -5,0\" style=\"fill: white;\"/></g><g class=\"markmap-link\" style=\"fill:none;\"><path stroke=\"#ff7f0e\" stroke-width=\"6\" d=\"M216,166.75 L221,166.75 C257,166.75 252,109.25 288,109.25 L290,109.25\"/><polygon class=\"markmap-link-polygon\" stroke-width=\"0\" transform=\"translate(216, 166.75)\" points=\"0,-3 5,0 0,3 -5,0\" style=\"fill: white;\"/></g><g class=\"markmap-link\" style=\"fill:none;\"><path stroke=\"#ff7f0e\" stroke-width=\"6\" d=\"M216,166.75 L221,166.75 C257,166.75 252,63.25 288,63.25 L290,63.25\"/><polygon class=\"markmap-link-polygon\" stroke-width=\"0\" transform=\"translate(216, 166.75)\" points=\"0,-3 5,0 0,3 -5,0\" style=\"fill: white;\"/></g><g class=\"markmap-link\" style=\"fill:none;\"><path stroke=\"#aec7e8\" stroke-width=\"6\" d=\"M-18,-19.549999999999997 L-13,-19.549999999999997 C59,-19.549999999999997 54,212.75 90,212.75 L92,212.75\"/><polygon class=\"markmap-link-polygon\" stroke-width=\"0\" transform=\"translate(-18, -19.549999999999997)\" points=\"0,-3 5,0 0,3 -5,0\" style=\"fill: white;\"/></g><g class=\"markmap-link\" style=\"fill:none;\"><path stroke=\"#ff7f0e\" stroke-width=\"6\" d=\"M-18,-19.549999999999997 L-13,-19.549999999999997 C59,-19.549999999999997 54,166.75 90,166.75 L92,166.75\"/><polygon class=\"markmap-link-polygon\" stroke-width=\"0\" transform=\"translate(-18, -19.549999999999997)\" points=\"0,-3 5,0 0,3 -5,0\" style=\"fill: white;\"/></g><g class=\"markmap-link\" style=\"fill:none;\"><path stroke=\"#ffbb78\" stroke-width=\"6\" d=\"M-18,-19.549999999999997 L-13,-19.549999999999997 C59,-19.549999999999997 54,-40.25 90,-40.25 L92,-40.25\"/><polygon class=\"markmap-link-polygon\" stroke-width=\"0\" transform=\"translate(-18, -19.549999999999997)\" points=\"0,-3 5,0 0,3 -5,0\" style=\"fill: white;\"/></g><g class=\"markmap-link\" style=\"fill:none;\"><path stroke=\"#2ca02c\" stroke-width=\"6\" d=\"M-18,-19.549999999999997 L-13,-19.549999999999997 C59,-19.549999999999997 54,-178.25 90,-178.25 L92,-178.25\"/><polygon class=\"markmap-link-polygon\" stroke-width=\"0\" transform=\"translate(-18, -19.549999999999997)\" points=\"0,-3 5,0 0,3 -5,0\" style=\"fill: white;\"/></g><g class=\"markmap-link\" style=\"fill:none;\"><path stroke=\"#98df8a\" stroke-width=\"6\" d=\"M-18,-19.549999999999997 L-13,-19.549999999999997 C59,-19.549999999999997 54,-258.75 90,-258.75 L92,-258.75\"/><polygon class=\"markmap-link-polygon\" stroke-width=\"0\" transform=\"translate(-18, -19.549999999999997)\" points=\"0,-3 5,0 0,3 -5,0\" style=\"fill: white;\"/></g><g class=\"markmap-node markmap-root-node\" transform=\"translate(-126,-19.549999999999997)\"><polygon class=\"markmap-node-polygon\" stroke-width=\"0\" transform=\"translate(107, 0)\" points=\"0,-3 5,0 0,3 -5,0\" style=\"fill: rgb(31, 119, 180);\"/><g transform=\"translate(1, -29)\"><rect class=\"markmap-node-rect\" rx=\"10\" ry=\"10\" height=\"58\" width=\"106\" fill=\"rgb(48, 183, 255)\" stroke=\"#1f77b4\" stroke-width=\"1\"/><text class=\"markmap-node-text\" alignment-baseline=\"middle\" dx=\"54\" dy=\"29\" text-anchor=\"middle\" style=\"font: bolder 14px sans-serif; fill-opacity: 1;\">章节标题编号</text></g></g><g class=\"markmap-node\" transform=\"translate(90,212.75)\"><line class=\"markmap-node-rect\" y1=\"0\" x1=\"0\" y2=\"0\" x2=\"27\" stroke-width=\"6\" stroke=\"#aec7e8\"/><polygon class=\"markmap-node-polygon\" stroke-width=\"0\" transform=\"translate(27, 0)\" points=\"0,-3 5,0 0,3 -5,0\" style=\"fill: rgb(174, 199, 232);\"/><a xlink:href=\"#e585b6e4bb96_24\"><text class=\"markmap-node-text\" dy=\"-5\" text-anchor=\"start\" x=\"10\" style=\"fill-opacity: 1; font: 14px sans-serif; fill: rgb(174, 199, 232); cursor: pointer;\">其他</text></a></g><g class=\"markmap-node\" transform=\"translate(90,166.75)\"><line class=\"markmap-node-rect\" y1=\"0\" x1=\"0\" y2=\"0\" x2=\"125\" stroke-width=\"6\" stroke=\"#ff7f0e\"/><polygon class=\"markmap-node-polygon\" stroke-width=\"0\" transform=\"translate(125, 0)\" points=\"0,-3 5,0 0,3 -5,0\" style=\"fill: rgb(255, 127, 14);\"/><a xlink:href=\"#e8a7a3e69e90e6b395e7aba0e88a82e6a087e9a298e7bc96e58fb7_13\"><text class=\"markmap-node-text\" dy=\"-5\" text-anchor=\"start\" x=\"10\" style=\"fill-opacity: 1; font: 14px sans-serif; fill: rgb(255, 127, 14); cursor: pointer;\">解析法章节标题编号</text></a></g><g class=\"markmap-node\" transform=\"translate(288,270.25)\"><line class=\"markmap-node-rect\" y1=\"0\" x1=\"0\" y2=\"0\" x2=\"41\" stroke-width=\"6\" stroke=\"#ff7f0e\"/><polygon class=\"markmap-node-polygon\" stroke-width=\"0\" transform=\"translate(41, 0)\" points=\"0,-3 5,0 0,3 -5,0\" style=\"fill: rgb(255, 127, 14);\"/><a xlink:href=\"#e4bc98e7bcbae782b9_21\"><text class=\"markmap-node-text\" dy=\"-5\" text-anchor=\"start\" x=\"10\" style=\"fill-opacity: 1; font: 14px sans-serif; fill: rgb(255, 127, 14); cursor: pointer;\">优缺点</text></a></g><g class=\"markmap-node\" transform=\"translate(402,293.25)\"><line class=\"markmap-node-rect\" y1=\"0\" x1=\"0\" y2=\"0\" x2=\"27\" stroke-width=\"6\" stroke=\"#ff7f0e\"/><polygon class=\"markmap-node-polygon\" stroke-width=\"0\" transform=\"translate(27, 0)\" points=\"0,-3 5,0 0,3 -5,0\" style=\"fill: rgb(255, 127, 14);\"/><a xlink:href=\"#e7bcbae782b9_23\"><text class=\"markmap-node-text\" dy=\"-5\" text-anchor=\"start\" x=\"10\" style=\"fill-opacity: 1; font: 14px sans-serif; fill: rgb(255, 127, 14); cursor: pointer;\">缺点</text></a></g><g class=\"markmap-node\" transform=\"translate(402,247.25)\"><line class=\"markmap-node-rect\" y1=\"0\" x1=\"0\" y2=\"0\" x2=\"27\" stroke-width=\"6\" stroke=\"#ff7f0e\"/><polygon class=\"markmap-node-polygon\" stroke-width=\"0\" transform=\"translate(27, 0)\" points=\"0,-3 5,0 0,3 -5,0\" style=\"fill: rgb(255, 127, 14);\"/><a xlink:href=\"#e4bc98e782b9_22\"><text class=\"markmap-node-text\" dy=\"-5\" text-anchor=\"start\" x=\"10\" style=\"fill-opacity: 1; font: 14px sans-serif; fill: rgb(255, 127, 14); cursor: pointer;\">优点</text></a></g><g class=\"markmap-node\" transform=\"translate(288,155.25)\"><line class=\"markmap-node-rect\" y1=\"0\" x1=\"0\" y2=\"0\" x2=\"55\" stroke-width=\"6\" stroke=\"#ff7f0e\"/><polygon class=\"markmap-node-polygon\" stroke-width=\"0\" transform=\"translate(55, 0)\" points=\"0,-3 5,0 0,3 -5,0\" style=\"fill: rgb(255, 127, 14);\"/><a xlink:href=\"#e9858de7bdaee8afb4e6988e_16\"><text class=\"markmap-node-text\" dy=\"-5\" text-anchor=\"start\" x=\"10\" style=\"fill-opacity: 1; font: 14px sans-serif; fill: rgb(255, 127, 14); cursor: pointer;\">配置说明</text></a></g><g class=\"markmap-node\" transform=\"translate(416,201.25)\"><line class=\"markmap-node-rect\" y1=\"0\" x1=\"0\" y2=\"0\" x2=\"41\" stroke-width=\"6\" stroke=\"#ff7f0e\"/><polygon class=\"markmap-node-polygon\" stroke-width=\"0\" transform=\"translate(41, 0)\" points=\"0,-3 5,0 0,3 -5,0\" style=\"fill: rgb(255, 127, 14);\"/><a xlink:href=\"#e58583e695b0e68dae_20\"><text class=\"markmap-node-text\" dy=\"-5\" text-anchor=\"start\" x=\"10\" style=\"fill-opacity: 1; font: 14px sans-serif; fill: rgb(255, 127, 14); cursor: pointer;\">元数据</text></a></g><g class=\"markmap-node\" transform=\"translate(416,155.25)\"><line class=\"markmap-node-rect\" y1=\"0\" x1=\"0\" y2=\"0\" x2=\"83\" stroke-width=\"6\" stroke=\"#ff7f0e\"/><polygon class=\"markmap-node-polygon\" stroke-width=\"0\" transform=\"translate(83, 0)\" points=\"0,-3 5,0 0,3 -5,0\" style=\"fill: rgb(255, 127, 14);\"/><a xlink:href=\"#e7bc96e58fb7e8aea1e7ae97e8a784e58899_19\"><text class=\"markmap-node-text\" dy=\"-5\" text-anchor=\"start\" x=\"10\" style=\"fill-opacity: 1; font: 14px sans-serif; fill: rgb(255, 127, 14); cursor: pointer;\">编号计算规则</text></a></g><g class=\"markmap-node\" transform=\"translate(416,109.25)\"><line class=\"markmap-node-rect\" y1=\"0\" x1=\"0\" y2=\"0\" x2=\"139\" stroke-width=\"6\" stroke=\"#ff7f0e\"/><polygon class=\"markmap-node-polygon\" stroke-width=\"0\" transform=\"translate(139, 0)\" points=\"0,-3 5,0 0,3 -5,0\" style=\"fill: rgb(255, 127, 14);\"/><a xlink:href=\"#e5a682e4bd95e4bfaee694b9e6a087e9a298e7bc96e58fb7e8a784e58899_17\"><text class=\"markmap-node-text\" dy=\"-5\" text-anchor=\"start\" x=\"10\" style=\"fill-opacity: 1; font: 14px sans-serif; fill: rgb(255, 127, 14); cursor: pointer;\">如何修改标题编号规则</text></a></g><g class=\"markmap-node\" transform=\"translate(628,109.25)\"><line class=\"markmap-node-rect\" y1=\"0\" x1=\"0\" y2=\"0\" x2=\"125\" stroke-width=\"6\" stroke=\"#ff7f0e\"/><polygon class=\"markmap-node-polygon\" stroke-width=\"0\" transform=\"translate(125, 0)\" points=\"0,-3 5,0 0,3 -5,0\" style=\"fill: rgb(255, 127, 14);\"/><a xlink:href=\"#e694afe68c81e79a84e7bc96e58fb7e698bee7a4bae6a0bce5bc8f_18\"><text class=\"markmap-node-text\" dy=\"-5\" text-anchor=\"start\" x=\"10\" style=\"fill-opacity: 1; font: 14px sans-serif; fill: rgb(255, 127, 14); cursor: pointer;\">支持的编号显示格式</text></a></g><g class=\"markmap-node\" transform=\"translate(288,109.25)\"><line class=\"markmap-node-rect\" y1=\"0\" x1=\"0\" y2=\"0\" x2=\"55\" stroke-width=\"6\" stroke=\"#ff7f0e\"/><polygon class=\"markmap-node-polygon\" stroke-width=\"0\" transform=\"translate(55, 0)\" points=\"0,-3 5,0 0,3 -5,0\" style=\"fill: rgb(255, 127, 14);\"/><a xlink:href=\"#e5bc80e590afe696b9e6b395_15\"><text class=\"markmap-node-text\" dy=\"-5\" text-anchor=\"start\" x=\"10\" style=\"fill-opacity: 1; font: 14px sans-serif; fill: rgb(255, 127, 14); cursor: pointer;\">开启方法</text></a></g><g class=\"markmap-node\" transform=\"translate(288,63.25)\"><line class=\"markmap-node-rect\" y1=\"0\" x1=\"0\" y2=\"0\" x2=\"55\" stroke-width=\"6\" stroke=\"#ff7f0e\"/><polygon class=\"markmap-node-polygon\" stroke-width=\"0\" transform=\"translate(55, 0)\" points=\"0,-3 5,0 0,3 -5,0\" style=\"fill: rgb(255, 127, 14);\"/><a xlink:href=\"#e5ae9ee78eb0e58e9fe79086_14\"><text class=\"markmap-node-text\" dy=\"-5\" text-anchor=\"start\" x=\"10\" style=\"fill-opacity: 1; font: 14px sans-serif; fill: rgb(255, 127, 14); cursor: pointer;\">实现原理</text></a></g><g class=\"markmap-node\" transform=\"translate(90,-40.25)\"><line class=\"markmap-node-rect\" y1=\"0\" x1=\"0\" y2=\"0\" x2=\"125\" stroke-width=\"6\" stroke=\"#ffbb78\"/><polygon class=\"markmap-node-polygon\" stroke-width=\"0\" transform=\"translate(125, 0)\" points=\"0,-3 5,0 0,3 -5,0\" style=\"fill: rgb(255, 187, 120);\"/><a xlink:href=\"#e6898be58699e6b395e7aba0e88a82e6a087e9a298e7bc96e58fb7_8\"><text class=\"markmap-node-text\" dy=\"-5\" text-anchor=\"start\" x=\"10\" style=\"fill-opacity: 1; font: 14px sans-serif; fill: rgb(255, 187, 120); cursor: pointer;\">手写法章节标题编号</text></a></g><g class=\"markmap-node\" transform=\"translate(288,-5.75)\"><line class=\"markmap-node-rect\" y1=\"0\" x1=\"0\" y2=\"0\" x2=\"41\" stroke-width=\"6\" stroke=\"#ffbb78\"/><polygon class=\"markmap-node-polygon\" stroke-width=\"0\" transform=\"translate(41, 0)\" points=\"0,-3 5,0 0,3 -5,0\" style=\"fill: rgb(255, 187, 120);\"/><a xlink:href=\"#e4bc98e7bcbae782b9_10\"><text class=\"markmap-node-text\" dy=\"-5\" text-anchor=\"start\" x=\"10\" style=\"fill-opacity: 1; font: 14px sans-serif; fill: rgb(255, 187, 120); cursor: pointer;\">优缺点</text></a></g><g class=\"markmap-node\" transform=\"translate(402,17.25)\"><line class=\"markmap-node-rect\" y1=\"0\" x1=\"0\" y2=\"0\" x2=\"27\" stroke-width=\"6\" stroke=\"#ffbb78\"/><polygon class=\"markmap-node-polygon\" stroke-width=\"0\" transform=\"translate(27, 0)\" points=\"0,-3 5,0 0,3 -5,0\" style=\"fill: rgb(255, 187, 120);\"/><a xlink:href=\"#e7bcbae782b9_12\"><text class=\"markmap-node-text\" dy=\"-5\" text-anchor=\"start\" x=\"10\" style=\"fill-opacity: 1; font: 14px sans-serif; fill: rgb(255, 187, 120); cursor: pointer;\">缺点</text></a></g><g class=\"markmap-node\" transform=\"translate(402,-28.75)\"><line class=\"markmap-node-rect\" y1=\"0\" x1=\"0\" y2=\"0\" x2=\"27\" stroke-width=\"6\" stroke=\"#ffbb78\"/><polygon class=\"markmap-node-polygon\" stroke-width=\"0\" transform=\"translate(27, 0)\" points=\"0,-3 5,0 0,3 -5,0\" style=\"fill: rgb(255, 187, 120);\"/><a xlink:href=\"#e4bc98e782b9_11\"><text class=\"markmap-node-text\" dy=\"-5\" text-anchor=\"start\" x=\"10\" style=\"fill-opacity: 1; font: 14px sans-serif; fill: rgb(255, 187, 120); cursor: pointer;\">优点</text></a></g><g class=\"markmap-node\" transform=\"translate(288,-74.75)\"><line class=\"markmap-node-rect\" y1=\"0\" x1=\"0\" y2=\"0\" x2=\"55\" stroke-width=\"6\" stroke=\"#ffbb78\"/><polygon class=\"markmap-node-polygon\" stroke-width=\"0\" transform=\"translate(55, 0)\" points=\"0,-3 5,0 0,3 -5,0\" style=\"fill: rgb(255, 187, 120);\"/><a xlink:href=\"#e5ae9ee78eb0e696b9e6b395_9\"><text class=\"markmap-node-text\" dy=\"-5\" text-anchor=\"start\" x=\"10\" style=\"fill-opacity: 1; font: 14px sans-serif; fill: rgb(255, 187, 120); cursor: pointer;\">实现方法</text></a></g><g class=\"markmap-node\" transform=\"translate(90,-178.25)\"><line class=\"markmap-node-rect\" y1=\"0\" x1=\"0\" y2=\"0\" x2=\"125\" stroke-width=\"6\" stroke=\"#2ca02c\"/><polygon class=\"markmap-node-polygon\" stroke-width=\"0\" transform=\"translate(125, 0)\" points=\"0,-3 5,0 0,3 -5,0\" style=\"fill: rgb(44, 160, 44);\"/><a xlink:href=\"#e6a0b7e5bc8fe6b395e7aba0e88a82e6a087e9a298e7bc96e58fb7_3\"><text class=\"markmap-node-text\" dy=\"-5\" text-anchor=\"start\" x=\"10\" style=\"fill-opacity: 1; font: 14px sans-serif; fill: rgb(44, 160, 44); cursor: pointer;\">样式法章节标题编号</text></a></g><g class=\"markmap-node\" transform=\"translate(288,-143.75)\"><line class=\"markmap-node-rect\" y1=\"0\" x1=\"0\" y2=\"0\" x2=\"41\" stroke-width=\"6\" stroke=\"#2ca02c\"/><polygon class=\"markmap-node-polygon\" stroke-width=\"0\" transform=\"translate(41, 0)\" points=\"0,-3 5,0 0,3 -5,0\" style=\"fill: rgb(44, 160, 44);\"/><a xlink:href=\"#e4bc98e7bcbae782b9_5\"><text class=\"markmap-node-text\" dy=\"-5\" text-anchor=\"start\" x=\"10\" style=\"fill-opacity: 1; font: 14px sans-serif; fill: rgb(44, 160, 44); cursor: pointer;\">优缺点</text></a></g><g class=\"markmap-node\" transform=\"translate(402,-120.75)\"><line class=\"markmap-node-rect\" y1=\"0\" x1=\"0\" y2=\"0\" x2=\"27\" stroke-width=\"6\" stroke=\"#2ca02c\"/><polygon class=\"markmap-node-polygon\" stroke-width=\"0\" transform=\"translate(27, 0)\" points=\"0,-3 5,0 0,3 -5,0\" style=\"fill: rgb(44, 160, 44);\"/><a xlink:href=\"#e7bcbae782b9_7\"><text class=\"markmap-node-text\" dy=\"-5\" text-anchor=\"start\" x=\"10\" style=\"fill-opacity: 1; font: 14px sans-serif; fill: rgb(44, 160, 44); cursor: pointer;\">缺点</text></a></g><g class=\"markmap-node\" transform=\"translate(402,-166.75)\"><line class=\"markmap-node-rect\" y1=\"0\" x1=\"0\" y2=\"0\" x2=\"27\" stroke-width=\"6\" stroke=\"#2ca02c\"/><polygon class=\"markmap-node-polygon\" stroke-width=\"0\" transform=\"translate(27, 0)\" points=\"0,-3 5,0 0,3 -5,0\" style=\"fill: rgb(44, 160, 44);\"/><a xlink:href=\"#e4bc98e782b9_6\"><text class=\"markmap-node-text\" dy=\"-5\" text-anchor=\"start\" x=\"10\" style=\"fill-opacity: 1; font: 14px sans-serif; fill: rgb(44, 160, 44); cursor: pointer;\">优点</text></a></g><g class=\"markmap-node\" transform=\"translate(288,-212.75)\"><line class=\"markmap-node-rect\" y1=\"0\" x1=\"0\" y2=\"0\" x2=\"55\" stroke-width=\"6\" stroke=\"#2ca02c\"/><polygon class=\"markmap-node-polygon\" stroke-width=\"0\" transform=\"translate(55, 0)\" points=\"0,-3 5,0 0,3 -5,0\" style=\"fill: rgb(44, 160, 44);\"/><a xlink:href=\"#e5ae9ee78eb0e696b9e6b395_4\"><text class=\"markmap-node-text\" dy=\"-5\" text-anchor=\"start\" x=\"10\" style=\"fill-opacity: 1; font: 14px sans-serif; fill: rgb(44, 160, 44); cursor: pointer;\">实现方法</text></a></g><g class=\"markmap-node\" transform=\"translate(90,-258.75)\"><line class=\"markmap-node-rect\" y1=\"0\" x1=\"0\" y2=\"0\" x2=\"27\" stroke-width=\"6\" stroke=\"#98df8a\"/><polygon class=\"markmap-node-polygon\" stroke-width=\"0\" transform=\"translate(27, 0)\" points=\"0,-3 5,0 0,3 -5,0\" style=\"fill: rgb(152, 223, 138);\"/><a xlink:href=\"#e6a682e8bfb0_1\"><text class=\"markmap-node-text\" dy=\"-5\" text-anchor=\"start\" x=\"10\" style=\"fill-opacity: 1; font: 14px sans-serif; fill: rgb(152, 223, 138); cursor: pointer;\">概述</text></a></g><g class=\"markmap-node\" transform=\"translate(190,-258.75)\"><line class=\"markmap-node-rect\" y1=\"0\" x1=\"0\" y2=\"0\" x2=\"181\" stroke-width=\"6\" stroke=\"#98df8a\"/><polygon class=\"markmap-node-polygon\" stroke-width=\"0\" transform=\"translate(181, 0)\" points=\"0,-3 5,0 0,3 -5,0\" style=\"fill: rgb(152, 223, 138);\"/><a xlink:href=\"#e6ada3e69687e6a087e9a298e7bc96e58fb7e79a84e587a0e7a78de5ae9ee78eb0e696b9e5bc8f_2\"><text class=\"markmap-node-text\" dy=\"-5\" text-anchor=\"start\" x=\"10\" style=\"fill-opacity: 1; font: 14px sans-serif; fill: rgb(152, 223, 138); cursor: pointer;\">正文标题编号的几种实现方式</text></a></g></g></svg></div></div><p></p>\n<div class=\"xiaoshujiang_element xsj_anchor\">\n  <a name=\"e6a682e8bfb0_1\" class=\"blank_anchor_name\"></a><a id=\"e6a682e8bfb0_1\" class=\"blank_anchor_id\"></a><a name=\"概述\" class=\"blank_anchor_name\"></a><a id=\"概述\" class=\"blank_anchor_id\"></a>\n</div>\n<h1 class=\"xsj_heading_hash xsj_heading xsj_heading_h1\"><span class=\"xsj_heading_content\">概述</span></h1>\n<p class=\"xsj_paragraph xsj_paragraph_level_0\">对文章内的章节标题进行编号，可以使文章有条有理，更眉目清楚，方便读者阅读文章同时，甚至对提高文章的质量还有帮助。</p>\n<p class=\"xsj_paragraph xsj_paragraph_level_0\">本文介绍了在小书匠编辑器下，章节标题编号的几种实现方案，并分析了各自优缺点。</p>\n<p class=\"xsj_paragraph xsj_paragraph_level_0\">特别介绍了印象笔记这个大家用得比较多的第三方存储如何实现章节标题自动编号的功能。</p>\n<div class=\"xiaoshujiang_element xsj_anchor\">\n  <a name=\"e6ada3e69687e6a087e9a298e7bc96e58fb7e79a84e587a0e7a78de5ae9ee78eb0e696b9e5bc8f_2\" class=\"blank_anchor_name\"></a><a id=\"e6ada3e69687e6a087e9a298e7bc96e58fb7e79a84e587a0e7a78de5ae9ee78eb0e696b9e5bc8f_2\" class=\"blank_anchor_id\"></a><a name=\"正文标题编号的几种实现方式\" class=\"blank_anchor_name\"></a><a id=\"正文标题编号的几种实现方式\" class=\"blank_anchor_id\"></a>\n</div>\n<h2 class=\"xsj_heading_hash xsj_heading xsj_heading_h2\"><span class=\"xsj_heading_content\">正文标题编号的几种实现方式</span></h2>\n<dl>\n<dt>样式法章节标题编号</dt>\n<dd>通过 css 自定义样式来实现</dd>\n<dt>解析法章节标题编号</dt>\n<dd>自己在 markdown 文章里手动输入</dd>\n<dt>手写法章节标题编号</dt>\n<dd>用户自己手动输入标题编号</dd>\n</dl>\n<div class=\"xiaoshujiang_element xsj_anchor\">\n  <a name=\"e6a0b7e5bc8fe6b395e7aba0e88a82e6a087e9a298e7bc96e58fb7_3\" class=\"blank_anchor_name\"></a><a id=\"e6a0b7e5bc8fe6b395e7aba0e88a82e6a087e9a298e7bc96e58fb7_3\" class=\"blank_anchor_id\"></a><a name=\"样式法章节标题编号\" class=\"blank_anchor_name\"></a><a id=\"样式法章节标题编号\" class=\"blank_anchor_id\"></a>\n</div>\n<h1 class=\"xsj_heading_hash xsj_heading xsj_heading_h1\"><span class=\"xsj_heading_content\">样式法章节标题编号</span></h1>\n<div class=\"xiaoshujiang_element xsj_anchor\">\n  <a name=\"e5ae9ee78eb0e696b9e6b395_4\" class=\"blank_anchor_name\"></a><a id=\"e5ae9ee78eb0e696b9e6b395_4\" class=\"blank_anchor_id\"></a><a name=\"实现方法\" class=\"blank_anchor_name\"></a><a id=\"实现方法\" class=\"blank_anchor_id\"></a>\n</div>\n<h2 class=\"xsj_heading_hash xsj_heading xsj_heading_h2\"><span class=\"xsj_heading_content\">实现方法</span></h2>\n<p class=\"xsj_paragraph xsj_paragraph_level_0\">通过自定义 css 样式来实现，可以参考下面的代码示例。需要用户对 html, css 有所了解。</p>\n<div class=\"xiaoshujiang_code_container\"><div class=\"xiaoshujiang_pre\"><div class=\"language-css hljs code_linenums xiaoshujiang_code\"><ol start=\"1\" class=\"ol_linenums\" style=\"counter-reset: lines 0;\"><li class=\"li_linenum \" date-linenum=\"1\"><span class=\"li_linenum_before_span li_linenum_before_span_hide\">1</span><span class=\"hljs-selector-tag\">body</span> {<span class=\"hljs-attribute\">counter-reset</span>: h1}&nbsp;<hr class=\"code_line_break_hack\" style=\"margin:0;border:0;border-top:0;border-bottom:0;\"></li><li class=\"li_linenum \" date-linenum=\"2\"><span class=\"li_linenum_before_span li_linenum_before_span_hide\">2</span>  <span class=\"hljs-selector-tag\">h1</span>{<span class=\"hljs-attribute\">counter-reset</span>: h2}&nbsp;<hr class=\"code_line_break_hack\" style=\"margin:0;border:0;border-top:0;border-bottom:0;\"></li><li class=\"li_linenum \" date-linenum=\"3\"><span class=\"li_linenum_before_span li_linenum_before_span_hide\">3</span>  <span class=\"hljs-selector-tag\">h2</span> {<span class=\"hljs-attribute\">counter-reset</span>: h3}&nbsp;<hr class=\"code_line_break_hack\" style=\"margin:0;border:0;border-top:0;border-bottom:0;\"></li><li class=\"li_linenum \" date-linenum=\"4\"><span class=\"li_linenum_before_span li_linenum_before_span_hide\">4</span>  <span class=\"hljs-selector-tag\">h3</span> {<span class=\"hljs-attribute\">counter-reset</span>: h4}&nbsp;<hr class=\"code_line_break_hack\" style=\"margin:0;border:0;border-top:0;border-bottom:0;\"></li><li class=\"li_linenum \" date-linenum=\"5\"><span class=\"li_linenum_before_span li_linenum_before_span_hide\">5</span>  <span class=\"hljs-selector-tag\">h4</span> {<span class=\"hljs-attribute\">counter-reset</span>: h5}&nbsp;<hr class=\"code_line_break_hack\" style=\"margin:0;border:0;border-top:0;border-bottom:0;\"></li><li class=\"li_linenum \" date-linenum=\"6\"><span class=\"li_linenum_before_span li_linenum_before_span_hide\">6</span>  <span class=\"hljs-selector-tag\">h5</span> {<span class=\"hljs-attribute\">counter-reset</span>: h6}&nbsp;<hr class=\"code_line_break_hack\" style=\"margin:0;border:0;border-top:0;border-bottom:0;\"></li><li class=\"li_linenum \" date-linenum=\"7\"><span class=\"li_linenum_before_span li_linenum_before_span_hide\">7</span>&nbsp;<hr class=\"code_line_break_hack\" style=\"margin:0;border:0;border-top:0;border-bottom:0;\"></li><li class=\"li_linenum \" date-linenum=\"8\"><span class=\"li_linenum_before_span li_linenum_before_span_hide\">8</span>  <span class=\"hljs-selector-tag\">h1</span><span class=\"hljs-selector-pseudo\">:before</span> {<span class=\"hljs-attribute\">counter-increment</span>: h1; <span class=\"hljs-attribute\">content</span>: <span class=\"hljs-built_in\">counter</span>(h1, cjk-ideographic) <span class=\"hljs-string\">\"、 \"</span>}&nbsp;<hr class=\"code_line_break_hack\" style=\"margin:0;border:0;border-top:0;border-bottom:0;\"></li><li class=\"li_linenum \" date-linenum=\"9\"><span class=\"li_linenum_before_span li_linenum_before_span_hide\">9</span>  <span class=\"hljs-selector-tag\">h2</span><span class=\"hljs-selector-pseudo\">:before</span> {<span class=\"hljs-attribute\">counter-increment</span>: h2; <span class=\"hljs-attribute\">content</span>: <span class=\"hljs-built_in\">counter</span>(h2) <span class=\"hljs-string\">\". \"</span>}&nbsp;<hr class=\"code_line_break_hack\" style=\"margin:0;border:0;border-top:0;border-bottom:0;\"></li><li class=\"li_linenum \" date-linenum=\"10\"><span class=\"li_linenum_before_span li_linenum_before_span_hide\">10</span>  <span class=\"hljs-selector-tag\">h3</span><span class=\"hljs-selector-pseudo\">:before</span> {<span class=\"hljs-attribute\">counter-increment</span>: h3; <span class=\"hljs-attribute\">content</span>: <span class=\"hljs-built_in\">counter</span>(h2) <span class=\"hljs-string\">\".\"</span> <span class=\"hljs-built_in\">counter</span>(h3) <span class=\"hljs-string\">\". \"</span>}&nbsp;<hr class=\"code_line_break_hack\" style=\"margin:0;border:0;border-top:0;border-bottom:0;\"></li><li class=\"li_linenum \" date-linenum=\"11\"><span class=\"li_linenum_before_span li_linenum_before_span_hide\">11</span>  <span class=\"hljs-selector-tag\">h4</span><span class=\"hljs-selector-pseudo\">:before</span> {<span class=\"hljs-attribute\">counter-increment</span>: h4; <span class=\"hljs-attribute\">content</span>: <span class=\"hljs-built_in\">counter</span>(h2) <span class=\"hljs-string\">\".\"</span> <span class=\"hljs-built_in\">counter</span>(h3) <span class=\"hljs-string\">\".\"</span> <span class=\"hljs-built_in\">counter</span>(h4) <span class=\"hljs-string\">\". \"</span>}&nbsp;<hr class=\"code_line_break_hack\" style=\"margin:0;border:0;border-top:0;border-bottom:0;\"></li><li class=\"li_linenum \" date-linenum=\"12\"><span class=\"li_linenum_before_span li_linenum_before_span_hide\">12</span>  <span class=\"hljs-selector-tag\">h5</span><span class=\"hljs-selector-pseudo\">:before</span> {<span class=\"hljs-attribute\">counter-increment</span>: h5; <span class=\"hljs-attribute\">content</span>: <span class=\"hljs-built_in\">counter</span>(h2) <span class=\"hljs-string\">\".\"</span> <span class=\"hljs-built_in\">counter</span>(h3) <span class=\"hljs-string\">\".\"</span> <span class=\"hljs-built_in\">counter</span>(h4) <span class=\"hljs-string\">\".\"</span> <span class=\"hljs-built_in\">counter</span>(h5) <span class=\"hljs-string\">\". \"</span>}&nbsp;<hr class=\"code_line_break_hack\" style=\"margin:0;border:0;border-top:0;border-bottom:0;\"></li><li class=\"li_linenum \" date-linenum=\"13\"><span class=\"li_linenum_before_span li_linenum_before_span_hide\">13</span>  <span class=\"hljs-selector-tag\">h6</span><span class=\"hljs-selector-pseudo\">:before</span> {<span class=\"hljs-attribute\">counter-increment</span>: h6; <span class=\"hljs-attribute\">content</span>: <span class=\"hljs-built_in\">counter</span>(h2) <span class=\"hljs-string\">\".\"</span> <span class=\"hljs-built_in\">counter</span>(h3) <span class=\"hljs-string\">\".\"</span> <span class=\"hljs-built_in\">counter</span>(h4) <span class=\"hljs-string\">\".\"</span> <span class=\"hljs-built_in\">counter</span>(h5) <span class=\"hljs-string\">\".\"</span> <span class=\"hljs-built_in\">counter</span>(h6) <span class=\"hljs-string\">\". \"</span>}&nbsp;<hr class=\"code_line_break_hack\" style=\"margin:0;border:0;border-top:0;border-bottom:0;\"></li><li class=\"li_linenum \" date-linenum=\"14\"><span class=\"li_linenum_before_span li_linenum_before_span_hide\">14</span>&nbsp;<hr class=\"code_line_break_hack\" style=\"margin:0;border:0;border-top:0;border-bottom:0;\"></li><li class=\"li_linenum \" date-linenum=\"15\"><span class=\"li_linenum_before_span li_linenum_before_span_hide\">15</span>  &nbsp;<hr class=\"code_line_break_hack\" style=\"margin:0;border:0;border-top:0;border-bottom:0;\"></li><li class=\"li_linenum \" date-linenum=\"16\"><span class=\"li_linenum_before_span li_linenum_before_span_hide\">16</span>  <span class=\"hljs-selector-tag\">h1</span><span class=\"hljs-selector-class\">.story_title</span><span class=\"hljs-selector-pseudo\">:before</span>,<span class=\"hljs-selector-tag\">h2</span><span class=\"hljs-selector-class\">.nocount</span><span class=\"hljs-selector-pseudo\">:before</span>, <span class=\"hljs-selector-tag\">h3</span><span class=\"hljs-selector-class\">.nocount</span><span class=\"hljs-selector-pseudo\">:before</span>, <span class=\"hljs-selector-tag\">h4</span><span class=\"hljs-selector-class\">.nocount</span><span class=\"hljs-selector-pseudo\">:before</span>, <span class=\"hljs-selector-tag\">h5</span><span class=\"hljs-selector-class\">.nocount</span><span class=\"hljs-selector-pseudo\">:before</span>, <span class=\"hljs-selector-tag\">h6</span><span class=\"hljs-selector-class\">.nocount</span><span class=\"hljs-selector-pseudo\">:before</span> { <span class=\"hljs-attribute\">content</span>: <span class=\"hljs-string\">\"\"</span>; <span class=\"hljs-attribute\">counter-increment</span>: none } &nbsp;<hr class=\"code_line_break_hack\" style=\"margin:0;border:0;border-top:0;border-bottom:0;\"></li></ol></div></div></div>\n<p class=\"xsj_paragraph xsj_paragraph_level_0\">更多相关 css 设置，可以参考<a href=\"https://github.com/suziwen/blogxiaoshujiang/blob/master/2017-9-24%20%E5%B0%8F%E4%B9%A6%E5%8C%A0%20pdf%20%E5%AF%BC%E5%87%BA%E8%87%AA%E5%AE%9A%E4%B9%89%20css%20%E6%95%99%E7%A8%8B.md\" class=\"xsj_link xsj_manu_link\">这里</a></p>\n<div class=\"xiaoshujiang_element xsj_anchor\">\n  <a name=\"e4bc98e7bcbae782b9_5\" class=\"blank_anchor_name\"></a><a id=\"e4bc98e7bcbae782b9_5\" class=\"blank_anchor_id\"></a><a name=\"优缺点\" class=\"blank_anchor_name\"></a><a id=\"优缺点\" class=\"blank_anchor_id\"></a>\n</div>\n<h2 class=\"xsj_heading_hash xsj_heading xsj_heading_h2\"><span class=\"xsj_heading_content\">优缺点</span></h2>\n<div class=\"xiaoshujiang_element xsj_anchor\">\n  <a name=\"e4bc98e782b9_6\" class=\"blank_anchor_name\"></a><a id=\"e4bc98e782b9_6\" class=\"blank_anchor_id\"></a><a name=\"优点\" class=\"blank_anchor_name\"></a><a id=\"优点\" class=\"blank_anchor_id\"></a>\n</div>\n<h3 class=\"xsj_heading_hash xsj_heading xsj_heading_h3\"><span class=\"xsj_heading_content\">优点</span></h3>\n<ol>\n<li>方便，大部份平台都支持</li>\n</ol>\n<div class=\"xiaoshujiang_element xsj_anchor\">\n  <a name=\"e7bcbae782b9_7\" class=\"blank_anchor_name\"></a><a id=\"e7bcbae782b9_7\" class=\"blank_anchor_id\"></a><a name=\"缺点\" class=\"blank_anchor_name\"></a><a id=\"缺点\" class=\"blank_anchor_id\"></a>\n</div>\n<h3 class=\"xsj_heading_hash xsj_heading xsj_heading_h3\"><span class=\"xsj_heading_content\">缺点</span></h3>\n<ol>\n<li>因为使用到了 css 里的 <code>content</code> 语法 ，需要通过外联式或者内嵌式来定义 css 才能实现。内联式 css 无法实现这种标题编号</li>\n<li>第三方存储保存文章时，如果要求使用内联式 css 存储正文时，标题编号将失效，比如印象笔记。</li>\n</ol>\n<div class=\"xiaoshujiang_element xsj_anchor\">\n  <a name=\"e6898be58699e6b395e7aba0e88a82e6a087e9a298e7bc96e58fb7_8\" class=\"blank_anchor_name\"></a><a id=\"e6898be58699e6b395e7aba0e88a82e6a087e9a298e7bc96e58fb7_8\" class=\"blank_anchor_id\"></a><a name=\"手写法章节标题编号\" class=\"blank_anchor_name\"></a><a id=\"手写法章节标题编号\" class=\"blank_anchor_id\"></a>\n</div>\n<h1 class=\"xsj_heading_hash xsj_heading xsj_heading_h1\"><span class=\"xsj_heading_content\">手写法章节标题编号</span></h1>\n<div class=\"xiaoshujiang_element xsj_anchor\">\n  <a name=\"e5ae9ee78eb0e696b9e6b395_9\" class=\"blank_anchor_name\"></a><a id=\"e5ae9ee78eb0e696b9e6b395_9\" class=\"blank_anchor_id\"></a><a name=\"实现方法\" class=\"blank_anchor_name\"></a><a id=\"实现方法\" class=\"blank_anchor_id\"></a>\n</div>\n<h2 class=\"xsj_heading_hash xsj_heading xsj_heading_h2\"><span class=\"xsj_heading_content\">实现方法</span></h2>\n<p class=\"xsj_paragraph xsj_paragraph_level_0\">就是自己手动维护章节标题编号</p>\n<div class=\"xiaoshujiang_element xsj_anchor\">\n  <a name=\"e4bc98e7bcbae782b9_10\" class=\"blank_anchor_name\"></a><a id=\"e4bc98e7bcbae782b9_10\" class=\"blank_anchor_id\"></a><a name=\"优缺点\" class=\"blank_anchor_name\"></a><a id=\"优缺点\" class=\"blank_anchor_id\"></a>\n</div>\n<h2 class=\"xsj_heading_hash xsj_heading xsj_heading_h2\"><span class=\"xsj_heading_content\">优缺点</span></h2>\n<div class=\"xiaoshujiang_element xsj_anchor\">\n  <a name=\"e4bc98e782b9_11\" class=\"blank_anchor_name\"></a><a id=\"e4bc98e782b9_11\" class=\"blank_anchor_id\"></a><a name=\"优点\" class=\"blank_anchor_name\"></a><a id=\"优点\" class=\"blank_anchor_id\"></a>\n</div>\n<h3 class=\"xsj_heading_hash xsj_heading xsj_heading_h3\"><span class=\"xsj_heading_content\">优点</span></h3>\n<ol>\n<li>灵活，完全按照自己的要求控制内容</li>\n</ol>\n<div class=\"xiaoshujiang_element xsj_anchor\">\n  <a name=\"e7bcbae782b9_12\" class=\"blank_anchor_name\"></a><a id=\"e7bcbae782b9_12\" class=\"blank_anchor_id\"></a><a name=\"缺点\" class=\"blank_anchor_name\"></a><a id=\"缺点\" class=\"blank_anchor_id\"></a>\n</div>\n<h3 class=\"xsj_heading_hash xsj_heading xsj_heading_h3\"><span class=\"xsj_heading_content\">缺点</span></h3>\n<ol>\n<li>缺点就是太麻烦， 标题没办法自动编号，一旦标题顺序需要调整时，就要对整篇文章的标题重新编号，工作最大</li>\n</ol>\n<div class=\"xiaoshujiang_element xsj_anchor\">\n  <a name=\"e8a7a3e69e90e6b395e7aba0e88a82e6a087e9a298e7bc96e58fb7_13\" class=\"blank_anchor_name\"></a><a id=\"e8a7a3e69e90e6b395e7aba0e88a82e6a087e9a298e7bc96e58fb7_13\" class=\"blank_anchor_id\"></a><a name=\"解析法章节标题编号\" class=\"blank_anchor_name\"></a><a id=\"解析法章节标题编号\" class=\"blank_anchor_id\"></a>\n</div>\n<h1 class=\"xsj_heading_hash xsj_heading xsj_heading_h1\"><span class=\"xsj_heading_content\">解析法章节标题编号</span></h1>\n<div class=\"xiaoshujiang_element xsj_anchor\">\n  <a name=\"e5ae9ee78eb0e58e9fe79086_14\" class=\"blank_anchor_name\"></a><a id=\"e5ae9ee78eb0e58e9fe79086_14\" class=\"blank_anchor_id\"></a><a name=\"实现原理\" class=\"blank_anchor_name\"></a><a id=\"实现原理\" class=\"blank_anchor_id\"></a>\n</div>\n<h2 class=\"xsj_heading_hash xsj_heading xsj_heading_h2\"><span class=\"xsj_heading_content\">实现原理</span></h2>\n<p class=\"xsj_paragraph xsj_paragraph_level_0\">通过小书匠 markdown 解析引擎，对 markdown 文档里的标题进行自动编号。</p>\n<div class=\"xiaoshujiang_element xsj_anchor\">\n  <a name=\"e5bc80e590afe696b9e6b395_15\" class=\"blank_anchor_name\"></a><a id=\"e5bc80e590afe696b9e6b395_15\" class=\"blank_anchor_id\"></a><a name=\"开启方法\" class=\"blank_anchor_name\"></a><a id=\"开启方法\" class=\"blank_anchor_id\"></a>\n</div>\n<h2 class=\"xsj_heading_hash xsj_heading xsj_heading_h2\"><span class=\"xsj_heading_content\">开启方法</span></h2>\n<p class=\"xsj_paragraph xsj_paragraph_level_0\">在 <code>小书匠主按钮&gt;设置&gt;预览</code> 里，把 <code>标题编号</code> 功能选中，系统就会对每篇文章正文里的标题进行自动编号。或者也可以通过每篇文章的元数据<code>renderNumberedHeading</code>，把<code>标题编号</code>功能打开。</p>\n<p class=\"xsj_paragraph xsj_paragraph_level_0\">通过 <code>小书匠主按钮&gt;设置&gt;预览</code> 里 <code>标题编号</code> 的设置，会影响到所有文章的显示，通过每篇文章开头的元数据控制，可以实现更个性化的配置，满足更多样的文章需求。比如有些文章是小说类的，我想让一号标题显示成 <code>第 xx 章</code> ， 二号标题显示成 <code>第 xx 节</code> 等。但有些文章是技术类，或者英文文档类的，一号标题我想显示成大写的英文字母，或者阿拉伯数字。</p>\n<div class=\"xiaoshujiang_element xsj_anchor\">\n  <a name=\"e9858de7bdaee8afb4e6988e_16\" class=\"blank_anchor_name\"></a><a id=\"e9858de7bdaee8afb4e6988e_16\" class=\"blank_anchor_id\"></a><a name=\"配置说明\" class=\"blank_anchor_name\"></a><a id=\"配置说明\" class=\"blank_anchor_id\"></a>\n</div>\n<h2 class=\"xsj_heading_hash xsj_heading xsj_heading_h2\"><span class=\"xsj_heading_content\">配置说明</span></h2>\n<p class=\"xsj_paragraph xsj_paragraph_level_0\">解析法章节标题编号系统默认提供了一套配置，用户可以直接启动标题编号，系统就会按照默认规则生成相应的标题前缀内容。如果这些规则不能满足用户的需要，系统也提供了一些自定义规则，来达到个性化的标题编号功能</p>\n<div class=\"xiaoshujiang_element xsj_anchor\">\n  <a name=\"e5a682e4bd95e4bfaee694b9e6a087e9a298e7bc96e58fb7e8a784e58899_17\" class=\"blank_anchor_name\"></a><a id=\"e5a682e4bd95e4bfaee694b9e6a087e9a298e7bc96e58fb7e8a784e58899_17\" class=\"blank_anchor_id\"></a><a name=\"如何修改标题编号规则\" class=\"blank_anchor_name\"></a><a id=\"如何修改标题编号规则\" class=\"blank_anchor_id\"></a>\n</div>\n<h3 class=\"xsj_heading_hash xsj_heading xsj_heading_h3\"><span class=\"xsj_heading_content\">如何修改标题编号规则</span></h3>\n<ol>\n<li>可以在 <code>小书匠主按钮&gt;设置&gt;预览</code> 里，对一号标题到七号标题进行规则设置。</li>\n<li><code>counter(hx, str, format);</code> 该命令用来显示一个通过计数器生成的字符串，需要提供三个参数\n<ol>\n<li><code>hx</code> 表示要使用哪个计数器，计数器范围只能是 <code>h1,h2,h3,h4,h5,h6,h7</code> 中的一个</li>\n<li><code>format</code> 表示指定的计数器输出结果后显示的格式，比如是数字，或者中文，或者阿拉伯文等，支持的类型可以参考<code>支持的编号显示格式</code> 小节。如果为空，则默认使用数字。</li>\n<li><code>str</code> 表示计数器按照指定的格式后，显示的字符串，需要提供一个 <code>%s</code> 占位符，用来显示当前计数器的编号值。该编号值会根据你选择的 <code>format</code> 格式显示最终的结果。默认值为 <code>%s-</code></li>\n</ol>\n</li>\n<li>支持多级嵌套，比如 <code>counter('h2');counter('h3');counter('h4', '%s. ');</code>，需要注意的是，如果 <code>h2</code> 没有内容，就会直接不显示。</li>\n</ol>\n<div class=\"xiaoshujiang_element xsj_anchor\">\n  <a name=\"e694afe68c81e79a84e7bc96e58fb7e698bee7a4bae6a0bce5bc8f_18\" class=\"blank_anchor_name\"></a><a id=\"e694afe68c81e79a84e7bc96e58fb7e698bee7a4bae6a0bce5bc8f_18\" class=\"blank_anchor_id\"></a><a name=\"支持的编号显示格式\" class=\"blank_anchor_name\"></a><a id=\"支持的编号显示格式\" class=\"blank_anchor_id\"></a>\n</div>\n<h4 class=\"xsj_heading_hash xsj_heading xsj_heading_h4\"><span class=\"xsj_heading_content\">支持的编号显示格式</span></h4>\n<table class=\"table table-striped table-celled\">\n<thead>\n<tr>\n<th>Format</th>\n<th>Description</th>\n</tr>\n</thead>\n<tbody>\n<tr>\n<td><code>arabic-indic</code></td>\n<td>Eastern arabic numerals</td>\n</tr>\n<tr>\n<td><code>armenian</code>, <code>upper-armenian</code></td>\n<td>Traditional Armenian numbering</td>\n</tr>\n<tr>\n<td><code>bengali</code></td>\n<td>Bengali numerals</td>\n</tr>\n<tr>\n<td><code>cambodian</code>, <code>khmer</code></td>\n<td>Khmer numerals</td>\n</tr>\n<tr>\n<td><code>circle</code></td>\n<td>A hollow circle (for any number)</td>\n</tr>\n<tr>\n<td><code>cjk-earthly-branch</code></td>\n<td>Numbering used in a Chinese system for reckoning time based on the Chinese zodiac</td>\n</tr>\n<tr>\n<td><code>cjk-decimal</code></td>\n<td>Han decimal numbers</td>\n</tr>\n<tr>\n<td><code>cjk-heavenly-stem</code></td>\n<td>Chinese system of ordinals based on the ten days of the week</td>\n</tr>\n<tr>\n<td><code>cjk-ideographic</code></td>\n<td>CJK (Chinese-Japanese-Korean) ideographic numbering</td>\n</tr>\n<tr>\n<td><code>decimal</code></td>\n<td>Decimal numbers</td>\n</tr>\n<tr>\n<td><code>decimal-leading-zero</code></td>\n<td>Decimal numbers with a leading zero if there is only one digit</td>\n</tr>\n<tr>\n<td><code>devanagari</code></td>\n<td>Devanagari numerals</td>\n</tr>\n<tr>\n<td><code>disc</code></td>\n<td>A filled disc (for any number)</td>\n</tr>\n<tr>\n<td><code>ethiopic-numeric</code></td>\n<td>Ethiopic numbering</td>\n</tr>\n<tr>\n<td><code>georgian</code></td>\n<td>Traditional Georgian numbering</td>\n</tr>\n<tr>\n<td><code>gujarati</code></td>\n<td>Gujarati numerals</td>\n</tr>\n<tr>\n<td><code>gurmukhi</code></td>\n<td>Gurmuhki numerals</td>\n</tr>\n<tr>\n<td><code>hebrew</code></td>\n<td>Traditional Hebrew numbering</td>\n</tr>\n<tr>\n<td><code>hiragana</code></td>\n<td>Hiragana letters</td>\n</tr>\n<tr>\n<td><code>hiragana-iroha</code></td>\n<td>Hiragana letters in the old Japanese ordering</td>\n</tr>\n<tr>\n<td><code>japanese-formal</code></td>\n<td>Japanese formal numbering to be used in legal or financial document</td>\n</tr>\n<tr>\n<td><code>japanese-informal</code></td>\n<td>Japanese informal numbering</td>\n</tr>\n<tr>\n<td><code>kannada</code></td>\n<td>Kannada numerals</td>\n</tr>\n<tr>\n<td><code>katakana</code></td>\n<td>Katakana letters</td>\n</tr>\n<tr>\n<td><code>katakana-iroha</code></td>\n<td>Katakana letters in the old Japanese ordering</td>\n</tr>\n<tr>\n<td><code>khmer</code></td>\n<td>Khmer numerals</td>\n</tr>\n<tr>\n<td><code>korean-hangul-formal</code></td>\n<td>Korean hangul numbering</td>\n</tr>\n<tr>\n<td><code>korean-hanja-formal</code></td>\n<td>Formal Korean Han numbering</td>\n</tr>\n<tr>\n<td><code>korean-hanja-informal</code></td>\n<td>Korean Hanja numbering</td>\n</tr>\n<tr>\n<td><code>lao</code></td>\n<td>Lao numerals</td>\n</tr>\n<tr>\n<td><code>lower-alpha</code>, <code>lower-latin</code></td>\n<td>Lowercase ASCII letters</td>\n</tr>\n<tr>\n<td><code>lower-armenian</code></td>\n<td>Traditional Armenian numbering with lowercase letters</td>\n</tr>\n<tr>\n<td><code>lower-greek</code></td>\n<td>Lowercase classical Greek</td>\n</tr>\n<tr>\n<td><code>lower-roman</code></td>\n<td>Lowercase Roman numerals</td>\n</tr>\n<tr>\n<td><code>malayalam</code></td>\n<td>Malayalam numerals</td>\n</tr>\n<tr>\n<td><code>mongolian</code></td>\n<td>Mongolian numerals</td>\n</tr>\n<tr>\n<td><code>myanmar</code></td>\n<td>Burmese numerals</td>\n</tr>\n<tr>\n<td><code>none</code></td>\n<td>Nothing, returns an empty string</td>\n</tr>\n<tr>\n<td><code>oriya</code></td>\n<td>Oriya (Odia) numerals</td>\n</tr>\n<tr>\n<td><code>persian</code></td>\n<td>Persian numerals</td>\n</tr>\n<tr>\n<td><code>simp-chinese-formal</code></td>\n<td>Simplified Chinese formal numbering</td>\n</tr>\n<tr>\n<td><code>simp-chinese-informal</code></td>\n<td>Simplified Chinese informal numbering</td>\n</tr>\n<tr>\n<td><code>square</code></td>\n<td>A filled square (for any number)</td>\n</tr>\n<tr>\n<td><code>tamil</code></td>\n<td>Tamil numerals</td>\n</tr>\n<tr>\n<td><code>telugu</code></td>\n<td>Telugu numerals</td>\n</tr>\n<tr>\n<td><code>thai</code></td>\n<td>Thai numerals</td>\n</tr>\n<tr>\n<td><code>tibetan</code></td>\n<td>Tibetan numerals</td>\n</tr>\n<tr>\n<td><code>trad-chinese-formal</code></td>\n<td>Traditional Chinese formal numbering</td>\n</tr>\n<tr>\n<td><code>trad-chinese-informal</code></td>\n<td>Traditional Chinese informal numbering</td>\n</tr>\n<tr>\n<td><code>upper-alpha</code>, <code>upper-latin</code></td>\n<td>Uppercase ASCII letters</td>\n</tr>\n<tr>\n<td><code>upper-armenian</code>, <code>armenian</code></td>\n<td>Traditional Armenian numbering</td>\n</tr>\n<tr>\n<td><code>upper-roman</code></td>\n<td>Uppercase Roman numerals</td>\n</tr>\n</tbody>\n</table>\n<div class=\"xiaoshujiang_element xsj_anchor\">\n  <a name=\"e7bc96e58fb7e8aea1e7ae97e8a784e58899_19\" class=\"blank_anchor_name\"></a><a id=\"e7bc96e58fb7e8aea1e7ae97e8a784e58899_19\" class=\"blank_anchor_id\"></a><a name=\"编号计算规则\" class=\"blank_anchor_name\"></a><a id=\"编号计算规则\" class=\"blank_anchor_id\"></a>\n</div>\n<h3 class=\"xsj_heading_hash xsj_heading xsj_heading_h3\"><span class=\"xsj_heading_content\">编号计算规则</span></h3>\n<ol>\n<li>系统只提供 <code>h1,h2,h3,h4,h5,h6,h7</code> 这七种计数器，与文章里的标题语法 <code>#,##,..</code> 分别对应 。</li>\n<li><code>h1 到 h7</code> 计数器各自独立编号。</li>\n<li>从<code>h1 到 h7</code> 计数器里，它们的权重依次由大到小， <code>h1</code> 计数器的权重最大， <code>h7</code> 计数器的权重最小。</li>\n<li>从 <code>h1 到 h7</code> ，高权重计数器会重置所有比它小的权重计数器， 比如当正文遇到 <code>##</code> 标题时，将会触发<code>h3</code> 计数器，同时将权重比 <code>h3</code> 小的计数器 <code>h4 到 h7</code> 重新置为初始值， 但不会重置比 <code>h3</code> 权重大的计数器 <code>h1</code> 和 <code>h2</code>。</li>\n<li>计数器递增值为 1。也就是正文里相临的两个同级标题，后面出现的标题会将对应的计数器自动加 1。</li>\n<li>计数器的数值递增是按照正文里遇到对应的标题触发，不是根据你使用了多少次<code>counter</code>方法来计算的。</li>\n</ol>\n<div class=\"xiaoshujiang_element xsj_anchor\">\n  <a name=\"e58583e695b0e68dae_20\" class=\"blank_anchor_name\"></a><a id=\"e58583e695b0e68dae_20\" class=\"blank_anchor_id\"></a><a name=\"元数据\" class=\"blank_anchor_name\"></a><a id=\"元数据\" class=\"blank_anchor_id\"></a>\n</div>\n<h3 class=\"xsj_heading_hash xsj_heading xsj_heading_h3\"><span class=\"xsj_heading_content\">元数据</span></h3>\n<div class=\"xiaoshujiang_code_container\"><div class=\"xiaoshujiang_pre\"><div class=\"nohighlight hljs code_linenums xiaoshujiang_code\"><ol start=\"1\" class=\"ol_linenums\" style=\"counter-reset: lines 0;\"><li class=\"li_linenum \" date-linenum=\"1\"><span class=\"li_linenum_before_span li_linenum_before_span_hide\">1</span>renderNumberedHeading: [true / false]  true 表示打开标题自动编号功能， false 表示关闭标题自动编号功能&nbsp;<hr class=\"code_line_break_hack\" style=\"margin:0;border:0;border-top:0;border-bottom:0;\"></li><li class=\"li_linenum \" date-linenum=\"2\"><span class=\"li_linenum_before_span li_linenum_before_span_hide\">2</span>renderNumberedHeadingOffset: '0,0,0,0,,,' ，各级计数器的起始值，以逗号分隔，分别表示从 h1 到 h7 的起始值,默认都为 0&nbsp;<hr class=\"code_line_break_hack\" style=\"margin:0;border:0;border-top:0;border-bottom:0;\"></li><li class=\"li_linenum \" date-linenum=\"3\"><span class=\"li_linenum_before_span li_linenum_before_span_hide\">3</span>renderNumberedHeadingH1: [字符串] 输入的字符串需要符合 `如何修改标题编号规则` 小节里的描述&nbsp;<hr class=\"code_line_break_hack\" style=\"margin:0;border:0;border-top:0;border-bottom:0;\"></li><li class=\"li_linenum \" date-linenum=\"4\"><span class=\"li_linenum_before_span li_linenum_before_span_hide\">4</span>renderNumberedHeadingH2:&nbsp;<hr class=\"code_line_break_hack\" style=\"margin:0;border:0;border-top:0;border-bottom:0;\"></li><li class=\"li_linenum \" date-linenum=\"5\"><span class=\"li_linenum_before_span li_linenum_before_span_hide\">5</span>renderNumberedHeadingH3:&nbsp;<hr class=\"code_line_break_hack\" style=\"margin:0;border:0;border-top:0;border-bottom:0;\"></li><li class=\"li_linenum \" date-linenum=\"6\"><span class=\"li_linenum_before_span li_linenum_before_span_hide\">6</span>....&nbsp;<hr class=\"code_line_break_hack\" style=\"margin:0;border:0;border-top:0;border-bottom:0;\"></li><li class=\"li_linenum \" date-linenum=\"7\"><span class=\"li_linenum_before_span li_linenum_before_span_hide\">7</span>renderNumberedHeadingH7:&nbsp;<hr class=\"code_line_break_hack\" style=\"margin:0;border:0;border-top:0;border-bottom:0;\"></li><li class=\"li_linenum \" date-linenum=\"8\"><span class=\"li_linenum_before_span li_linenum_before_span_hide\">8</span>&nbsp;<hr class=\"code_line_break_hack\" style=\"margin:0;border:0;border-top:0;border-bottom:0;\"></li><li class=\"li_linenum \" date-linenum=\"9\"><span class=\"li_linenum_before_span li_linenum_before_span_hide\">9</span>H1 到 H7 分别表示 正文里 `# 到 #######` 标题规则设置字符串&nbsp;<hr class=\"code_line_break_hack\" style=\"margin:0;border:0;border-top:0;border-bottom:0;\"></li></ol></div></div></div>\n<div class=\"xiaoshujiang_element xsj_anchor\">\n  <a name=\"e4bc98e7bcbae782b9_21\" class=\"blank_anchor_name\"></a><a id=\"e4bc98e7bcbae782b9_21\" class=\"blank_anchor_id\"></a><a name=\"优缺点\" class=\"blank_anchor_name\"></a><a id=\"优缺点\" class=\"blank_anchor_id\"></a>\n</div>\n<h2 class=\"xsj_heading_hash xsj_heading xsj_heading_h2\"><span class=\"xsj_heading_content\">优缺点</span></h2>\n<div class=\"xiaoshujiang_element xsj_anchor\">\n  <a name=\"e4bc98e782b9_22\" class=\"blank_anchor_name\"></a><a id=\"e4bc98e782b9_22\" class=\"blank_anchor_id\"></a><a name=\"优点\" class=\"blank_anchor_name\"></a><a id=\"优点\" class=\"blank_anchor_id\"></a>\n</div>\n<h3 class=\"xsj_heading_hash xsj_heading xsj_heading_h3\"><span class=\"xsj_heading_content\">优点</span></h3>\n<p class=\"xsj_paragraph xsj_paragraph_level_0\">可以对内联样式的文章进行标题编号，同时不需要自己手动维护</p>\n<div class=\"xiaoshujiang_element xsj_anchor\">\n  <a name=\"e7bcbae782b9_23\" class=\"blank_anchor_name\"></a><a id=\"e7bcbae782b9_23\" class=\"blank_anchor_id\"></a><a name=\"缺点\" class=\"blank_anchor_name\"></a><a id=\"缺点\" class=\"blank_anchor_id\"></a>\n</div>\n<h3 class=\"xsj_heading_hash xsj_heading xsj_heading_h3\"><span class=\"xsj_heading_content\">缺点</span></h3>\n<p class=\"xsj_paragraph xsj_paragraph_level_0\">小书匠独家支持，估计在其他 markdown 编辑器上不兼容。如果在多编辑器上使用，会有兼容性问题。</p>\n<div class=\"xiaoshujiang_element xsj_anchor\">\n  <a name=\"e585b6e4bb96_24\" class=\"blank_anchor_name\"></a><a id=\"e585b6e4bb96_24\" class=\"blank_anchor_id\"></a><a name=\"其他\" class=\"blank_anchor_name\"></a><a id=\"其他\" class=\"blank_anchor_id\"></a>\n</div>\n<h1 class=\"xsj_heading_hash xsj_heading xsj_heading_h1\"><span class=\"xsj_heading_content\">其他</span></h1>\n<p class=\"xsj_paragraph xsj_paragraph_level_0\">像印象笔记，evernote 或者发送邮件等，由于它们不提供外联式或者内嵌式样式定义的文章，导致用户通过<code>样式法章节标题编号</code>生成的标题编号失效，这个时候就可以考虑使用小书匠系统提供的<code>解析法章节标题编号</code>功能来实现对文章章节的标题编号。</p>\n<p class=\"xsj_paragraph xsj_paragraph_level_0\">不过大部份用户可能还是比较喜欢使用<code>样式法章节标题编号</code>，毕竟这是 w3c 提供的一种标准方案。但是又有把文章保存到印象笔记的需求，如果还想实现章节标题编号。这个时候用户如果同时使用了 <code>样式法</code> 和 <code>解析法</code> 两种方案，虽然在保存到印象笔记里的文章能够正常显示标题编号，但在小书匠预览窗内就显示出了重复的编号标题。</p>\n<p class=\"xsj_paragraph xsj_paragraph_level_0\">如何解决重复标题编号呢，小书匠系统还提供了另一种打开 <code>解析法章节标题编号</code> 功能，间接达到解决上述问题的方法。就是在 <code>绑定</code> 界面里，用户可以单独对印象笔记设置，当每次保存印象笔记时，强制使用 <code>解析法章节标题编号</code> 功能。该功能不受全局(<code>小书匠主按钮&gt;设置&gt;预览</code>)设置的影响，也不受每篇文章元数据里设置的控制。同时该功能在发送邮件时也提供了选项操作。</p>\n</div>\n\n","excerpt":"对文章内的章节标题进行编号，可以使文章有条有理，更眉目清楚，方便读者阅读文章同时，甚至对提高文章的质量还有帮助。\n本文介绍了在小书匠编辑器下，章节标题编号的几种实现方案，并分析了各自优缺点。\n特别介绍了印象笔记这个大家用得比较多的第三方存储如何实现章节标题自动编号的功能。\n通过自...","docType":"blogs","title":"2018-10-10 正文标题编号","customCss":"","css":"\nbody h1,p{line-height:1.6}body,pre{word-break:break-word}.tag.label,.xsj_mindmap_caption,kbd{display:inline-block}body,kbd{color:#2f2f2f}img,kbd{vertical-align:middle}address,blockquote small{display:block;line-height:20px}address,blockquote small,dd,dt{line-height:20px}.xiaoshujiang_pre,pre{word-wrap:break-word;tab-size:4;white-space:pre-wrap}.li_linenum,.xiaoshujiang_code.hljs.code_linenums,code.hljs.code_linenums{position:relative}img,table{max-width:100%}body{font-family:'Helvetica Neue',Helvetica,Tahoma,Arial,'Hiragino Sans GB',STHeiti,\"Microsoft YaHei\",\"微软雅黑\",'WenQuanYi Micro Hei',STXihei,\"华文细黑\",Heiti,\"黑体\",SimSun,\"宋体\",Song,sans-serif;font-size:16px;line-height:1.33;font-weight:100;word-wrap:break-word;letter-spacing:0;word-spacing:.25em}a:focus{outline:#333 dotted thin;outline:-webkit-focus-ring-color auto 5px;outline-offset:-2px}a:active,a:hover{outline:0}a{color:#08c;text-decoration:none}a:hover{color:#005580;text-decoration:underline}h1,h2,h3,h4,h5,h6{margin:1em 0 .6em;font-family:inherit;font-weight:500;line-height:2.35rem;color:inherit;text-rendering:optimizelegibility}.mermaid_svg,.xiaoshujiang_pre,pre{font-family:monospace}h1{font-size:3.4rem}h2{font-size:3rem}h3{font-size:2.45rem}h4{font-size:2.1rem}h5{font-size:1.9rem}h6{font-size:1.5rem}body h2,body h3{line-height:1.1}.xsj_hr{margin:20px 0;border:0;border-top:1px dashed #2f2f2f;border-left:90px solid transparent;border-right:90px solid transparent}address,dl{margin-bottom:20px}blockquote p,ol ol,ol ul,ul ol,ul ul{margin-bottom:0}p{margin:0 0 1.1em}pre{line-height:initial!important}kbd{padding:3px 5px;font-size:11px;line-height:10px;background-color:#fcfcfc;border:1px solid #2f2f2f;border-bottom-color:#2f2f2f;border-radius:3px;box-shadow:inset 0 -1px 0 #2f2f2f}address{font-style:normal}img{height:auto;border:0}table{background-color:transparent;border-collapse:collapse;border-spacing:0;word-break:initial;border:1px solid rgba(34,36,38,.15)}small{font-size:85%}dt,strong{font-weight:700}em{font-style:italic}cite{font-style:normal}ol,ul{padding:0;margin:0 0 10px 35px}dd{margin-left:10px}body dd,body dt{line-height:1.35em}abbr[data-original-title],abbr[title]{cursor:help;border-bottom:1px dotted #999}blockquote{padding:15px 20px;margin:0 0 20px;border-left:10px solid rgba(153,153,153,.3);background:rgba(204,204,204,.4)}blockquote p{font-size:16px;font-weight:300;line-height:25px}.table th,.tag.label{font-weight:700}blockquote small{color:#999}blockquote small:before{content:'\\2014 \\00A0'}blockquote footer{margin:1em 0;font-style:italic}blockquote footer cite{margin:0 1em}code{background-color:rgba(214,219,223,.28);color:#2C3E50;border-radius:4px;padding:2px 4px}body code{border:0;border-radius:4px;font-size:90%}text{font-size:14px}h1.story_title{margin:.7em 0}.story_tags{margin:0 0 1.2em}.tag.label{vertical-align:baseline;line-height:1;margin:.125em;background-color:#ebeeef;border-color:#ebeeef;background-image:none;padding:.6em .8em;color:#5e6060;text-transform:none;border-radius:.2857rem;box-sizing:border-box;font-size:12px}.table{width:100%;margin-bottom:20px;margin-right:auto;margin-left:auto}.table td,.table th{padding:8px;line-height:20px;text-align:left;vertical-align:top;border-top:1px solid #ddd}.table thead th{vertical-align:bottom}.table caption+thead tr:first-child td,.table caption+thead tr:first-child th,.table colgroup+thead tr:first-child td,.table colgroup+thead tr:first-child th,.table thead:first-child tr:first-child td,.table thead:first-child tr:first-child th{border-top:0}.table tbody+tbody{border-top:2px solid #ddd}.table .table{background-color:#fff}.table-striped tbody>tr:nth-child(odd)>td,.table-striped tbody>tr:nth-child(odd)>th{background-color:#f9f9f9}.table-celled.table tr td,.table-celled.table tr th{border-left:1px solid rgba(34,36,38,.1)}.table-celled.table tr td:first-child,.table-celled.table tr th:first-child{border-left:none}.mindmap_container{text-align:center}.xsj_mindmap_caption{border-bottom:1px solid #d9d9d9;color:#999;padding:10px}.hljs,.hljs *{overflow:visible!important}body .xiaoshujiang_code{border:0;border-radius:4px;font-size:90%}.xiaoshujiang_code ol{margin-bottom:0}.xiaoshujiang_pre{line-height:initial!important;word-break:break-word}.xiaoshujiang_code_container pre{margin:0}.xiaoshujiang_code_container.xiaoshujiang_code_chunk{box-shadow:0 0 0 1px #A3C293 inset,0 0 0 0 transparent;margin:1em 0;padding:1em}.xiaoshujiang_code_container.xiaoshujiang_code_chunk_hide_code{box-shadow:initial;padding:initial initial 2em}.xiaoshujiang_code_container .out_put{box-shadow:0 0 0 1px #A3C293 inset,0 0 0 0 transparent;margin:1em 0;background-color:#FCFFF5;padding:1em}.xiaoshujiang_code_container .out_put_error{background-color:#FFF6F6;color:#9F3A38;margin:1em 0;box-shadow:0 0 0 1px #E0B4B4 inset,0 0 0 0 transparent;padding:1em}.ol_linenums{padding:0;margin-left:2em;border-left:1px solid #e0e0e0}.li_linenum{padding-left:.5em;list-style:none;counter-increment:lines 1}.li_linenum.li_list_style{list-style:inherit;margin-left:5px}.li_linenum:before,.li_linenum_before_span{content:counter(lines,decimal);position:absolute;left:-2.5em;text-align:center;width:2.5em;vertical-align:top}.li_linenum_before_span_hide{display:none}.xiaoshujiang_code_container{margin:1em 0;position:relative;padding-bottom:2em}.xiaoshujiang_code_title_container{font-size:70%;opacity:.5}.xiaoshujiang_code_title_container>.xiaoshujiang_code_infos{float:right}.mark{border:0;background-color:rgba(221,243,231,.4);color:#29754d;padding:2px 4px}.line_mark{background-color:rgba(255,0,0,.1)}.li_linenum.line_mark:before,.line_mark .li_linenum_before_span{background-color:rgba(255,0,0,.3)}.xiaoshujiang_code .mark,code .mark{border-radius:0;font-size:initial;padding:initial;background-color:rgba(160,234,194,.7)}a.attachment{background-color:#ecf0f3;border:1px solid #bec6cb;display:inline-block;padding:5px;margin:2px;min-width:250px}a.attachment i.fa{font-size:3em;float:left;margin-right:.2em}a.attachment .filename{vertical-align:top;text-align:left;font-weight:700}.flow-chart,.mermaid,.plot,.plot-image,.sequence-diagram,.story_image_container,.story_remote_resource_block,.video_container{text-align:center}a.attachment .filesize{display:-webkit-box;display:-moz-box;display:-ms-flexbox;display:-webkit-flex;display:flex;opacity:.6;font-size:80%;white-space:nowrap}.story_image_caption,.story_inline_image{display:inline-block}.story_image_container>.story_image{display:inline-block;position:relative;max-width:100%}.story_image_caption{border-bottom:1px solid #d9d9d9;color:#999;padding:10px}.story_image_blank_caption{border-bottom:0}.story_image>img{border-radius:.3125em;box-shadow:0 2px 4px 0 rgba(34,36,38,.12),0 2px 10px 0 rgba(34,36,38,.08)}.story_inline_image>img{vertical-align:bottom}.task-list-item{list-style:none}.task-list-item.li_list_style{list-style:inherit}.task-list-item>input{margin:0 0 0 -20px}.video_container{width:100%;display:table;position:relative;padding-bottom:56.25%!important}.video_container iframe{width:100%;height:100%;position:absolute;top:0;left:0;z-index:1;vertical-align:middle}.slideshare_container .inner{position:relative;width:100%}.slideshare_container .inner iframe{width:100%;height:100%;position:absolute;top:0;bottom:0;left:0;right:0}.toc ul{list-style-type:none}em.cjk_emphasis{font-style:normal;font-family:Georgia,\"Times New Roman\",Times,\"楷体\",\"AR PL UKai CN\",NSimSun,\"Songti SC\",SimSun,serif!important}.plot,.plot-image{min-height:200px;min-width:200px}.story_align_left,.story_align_left .story_image_container{text-align:left}.story_align_right,.story_align_right .story_image_container{text-align:right}.story_align_center,.story_align_center .story_image_container{text-align:center}.story_align_justify,.story_align_justify .story_image_container{text-align:justify}.mathjax-container{text-align:center}div.mathjax{max-width:600px;margin:0 auto;font-size:14px}@media print{body{font-size:18px;word-wrap:break-word;word-break:break-word;background:initial;font-kerning:normal;text-rendering:geometricPrecision}.xiaoshujiang_element.xsj_anchor{position:absolute}.story_image_container,tr{page-break-inside:avoid}.xsj_underline{page-break-after:always;visibility:hidden}}\n/*\n\nOrginal Style from ethanschoonover.com/solarized (c) Jeremy Hull <sourdrums@gmail.com>\n\n*/\n\n.hljs {\n  display: block;\n  overflow-x: auto;\n  padding: 0.5em;\n  background: #fdf6e3;\n  color: #657b83;\n}\n\n.hljs-comment,\n.hljs-quote {\n  color: #93a1a1;\n}\n\n/* Solarized Green */\n.hljs-keyword,\n.hljs-selector-tag,\n.hljs-addition {\n  color: #859900;\n}\n\n/* Solarized Cyan */\n.hljs-number,\n.hljs-string,\n.hljs-meta .hljs-meta-string,\n.hljs-literal,\n.hljs-doctag,\n.hljs-regexp {\n  color: #2aa198;\n}\n\n/* Solarized Blue */\n.hljs-title,\n.hljs-section,\n.hljs-name,\n.hljs-selector-id,\n.hljs-selector-class {\n  color: #268bd2;\n}\n\n/* Solarized Yellow */\n.hljs-attribute,\n.hljs-attr,\n.hljs-variable,\n.hljs-template-variable,\n.hljs-class .hljs-title,\n.hljs-type {\n  color: #b58900;\n}\n\n/* Solarized Orange */\n.hljs-symbol,\n.hljs-bullet,\n.hljs-subst,\n.hljs-meta,\n.hljs-meta .hljs-keyword,\n.hljs-selector-attr,\n.hljs-selector-pseudo,\n.hljs-link {\n  color: #cb4b16;\n}\n\n/* Solarized Red */\n.hljs-built_in,\n.hljs-deletion {\n  color: #dc322f;\n}\n\n.hljs-formula {\n  background: #eee8d5;\n}\n\n.hljs-emphasis {\n  font-style: italic;\n}\n\n.hljs-strong {\n  font-weight: bold;\n}\n\n/**\n * Treeview syntax highlighting based on highlight.js\n * Copyright (c) 2014-2015, Asciidocfx Team, (MIT Licensed)\n * https://github.com/asciidocfx/highlight-treeview.js\n */\n.language-treeview.hljs{\n  position: relative;\n}\n.hljs-folder,\n.hljs-hiddenfile,\n.hljs-file {\n    position: relative;\n    vertical-align: top;\n    display: inline-block;\n    height: 16px;\n}\n.hljs-folder:before,\n.hljs-file:before,\n.hljs-hiddenfile:before {\n    top: 0;\n    content: '';\n    width: 14px;\n    height: 12px;\n    margin-top: 0px;\n    margin-right: 3px;\n    position: relative;\n    display: inline-block;\n    background-size: 14px;\n    background-repeat: no-repeat;\n}\n.hljs-file:before,\n.hljs-hiddenfile:before {\n    height: 14px;\n    margin-left: 1px;\n}\n.hljs-hiddenfile {\n    opacity: 0.6;\n}\n.hljs-file.photo:before {\n    font: normal normal normal 14px/1 FontAwesome;\n    content: \"\\f1c5\";\n}\n.hljs-file.plain:before {\n    font: normal normal normal 14px/1 FontAwesome;\n    content: \"\\f016\";\n}\n.hljs-file.source:before {\n    font: normal normal normal 14px/1 FontAwesome;\n    content: \"\\f1c9\";\n}\n.hljs-file.archive:before {\n    font: normal normal normal 14px/1 FontAwesome;\n    content: \"\\f1c6\";\n}\n.hljs-file.audio:before {\n    font: normal normal normal 14px/1 FontAwesome;\n    content: \"\\f1c7\";\n}\n.hljs-file.video:before {\n    font: normal normal normal 14px/1 FontAwesome;\n    content: \"\\f1c8\";\n}\n.hljs-file.pdf:before {\n    font: normal normal normal 14px/1 FontAwesome;\n    content: \"\\f1c1\";\n}\n.hljs-file.xls:before {\n    font: normal normal normal 14px/1 FontAwesome;\n    content: \"\\f1c3\";\n}\n.hljs-file.doc:before {\n    font: normal normal normal 14px/1 FontAwesome;\n    content: \"\\f1c2\";\n}\n.hljs-file.ppt:before {\n    font: normal normal normal 14px/1 FontAwesome;\n    content: \"\\f1c4\";\n}\n.hljs-folder:before {\n    font: normal normal normal 14px/1 FontAwesome;\n    content: \"\\f114\";\n}\n.hljs-hiddenfile:before {\n    font: normal normal normal 14px/1 FontAwesome;\n    content: \"\\f016\";\n}\n.hljs-tvline {\n    margin-left: 6px;\n    position: absolute;\n    text-indent: -99em;\n    padding-bottom: 8px;\n    vertical-align: top;\n    display: inline-block;\n    border-left-width: 1px;\n    border-left-style: solid;\n    border-left-color: rgb(94, 144, 117);\n}\n.hljs-folder-branch {\n    width: 8px;\n    height: 8px;\n    margin-top: -1px;\n    margin-left: 6px;\n    text-indent: -99em;\n    position: relative;\n    vertical-align: top;\n    display: inline-block;\n    border-bottom-width: 1px;\n    border-bottom-style: solid;\n    border-bottom-color: rgb(94, 144, 117);\n}\n.hljs-folder-branch.win {\n    width: 14px;\n    margin-right: 2px;\n}\n.hljs-folder-last-branch {\n    height: 7px;\n    width: 7px;\n    margin-left: 6px;\n    text-indent: -99em;\n    position: relative;\n    vertical-align: top;\n    display: inline-block;\n    border-bottom-width: 1px;\n    border-bottom-style: solid;\n    border-bottom-color: rgb(94, 144, 117);\n    border-left-width: 1px;\n    border-left-style: solid;\n    border-left-color: rgb(94, 144, 117);\n}\n.hljs-folder-last-branch.win {\n    width: 13px;\n    margin-right: 2px;\n}\n\n\n/**\n * Treeview syntax highlighting based on highlight.js\n */\n\n/*wavedrom start*/\n\n.wavedrom_svg text, .wavedrom_svg_defs text {\n    font-size:11pt;\n    font-style:normal;\n    font-variant:normal;\n    font-weight:normal;\n    font-stretch:normal;\n    text-align:center;\n    fill-opacity:1;\n    font-family:Helvetica\n}\n.wavedrom_svg .muted, .wavedrom_svg_defs .muted {\n    fill:#aaa\n}\n.wavedrom_svg .warning, .wavedrom_svg_defs .warning {\n    fill:#f6b900\n}\n.wavedrom_svg .error, .wavedrom_svg_defs .error {\n    fill:#f60000\n}\n.wavedrom_svg .info, .wavedrom_svg_defs .info {\n    fill:#0041c4\n}\n.wavedrom_svg .success, .wavedrom_svg_defs .success {\n    fill:#00ab00\n}\n.wavedrom_svg .h1, .wavedrom_svg_defs .h1 {\n    font-size:33pt;\n    font-weight:bold\n}\n.wavedrom_svg .h2, .wavedrom_svg_defs .h2 {\n    font-size:27pt;\n    font-weight:bold\n}\n.wavedrom_svg .h3, .wavedrom_svg_defs .h3 {\n    font-size:20pt;\n    font-weight:bold\n}\n.wavedrom_svg .h4, .wavedrom_svg_defs .h4 {\n    font-size:14pt;\n    font-weight:bold\n}\n.wavedrom_svg .h5, .wavedrom_svg_defs .h5 {\n    font-size:11pt;\n    font-weight:bold\n}\n.wavedrom_svg .h6, .wavedrom_svg_defs .h6 {\n    font-size:8pt;\n    font-weight:bold\n}\n.wavedrom_svg_defs .s1 {\n    fill:none;\n    stroke:#000;\n    stroke-width:1;\n    stroke-linecap:round;\n    stroke-linejoin:miter;\n    stroke-miterlimit:4;\n    stroke-opacity:1;\n    stroke-dasharray:none\n}\n.wavedrom_svg_defs .s2 {\n    fill:none;\n    stroke:#000;\n    stroke-width:0.5;\n    stroke-linecap:round;\n    stroke-linejoin:miter;\n    stroke-miterlimit:4;\n    stroke-opacity:1;\n    stroke-dasharray:none\n}\n.wavedrom_svg_defs .s3 {\n    color:#000;\n    fill:none;\n    stroke:#000;\n    stroke-width:1;\n    stroke-linecap:round;\n    stroke-linejoin:miter;\n    stroke-miterlimit:4;\n    stroke-opacity:1;\n    stroke-dasharray:1,3;\n    stroke-dashoffset:0;\n    marker:none;\n    visibility:visible;\n    display:inline;\n    overflow:visible;\n    enable-background:accumulate\n}\n.wavedrom_svg_defs .s4 {\n    color:#000;\n    fill:none;\n    stroke:#000;\n    stroke-width:1;\n    stroke-linecap:round;\n    stroke-linejoin:miter;\n    stroke-miterlimit:4;\n    stroke-opacity:1;\n    stroke-dasharray:none;\n    stroke-dashoffset:0;\n    marker:none;\n    visibility:visible;\n    display:inline;\n    overflow:visible\n}\n.wavedrom_svg_defs .s5 {\n    fill:#fff;\n    stroke:none\n}\n.wavedrom_svg_defs .s6 {\n    color:#000;\n    fill:#ffffb4;\n    fill-opacity:1;\n    fill-rule:nonzero;\n    stroke:none;\n    stroke-width:1px;\n    marker:none;\n    visibility:visible;\n    display:inline;\n    overflow:visible;\n    enable-background:accumulate\n}\n.wavedrom_svg_defs .s7 {\n    color:#000;\n    fill:#ffe0b9;\n    fill-opacity:1;\n    fill-rule:nonzero;\n    stroke:none;\n    stroke-width:1px;\n    marker:none;\n    visibility:visible;\n    display:inline;\n    overflow:visible;\n    enable-background:accumulate\n}\n.wavedrom_svg_defs .s8 {\n    color:#000;\n    fill:#b9e0ff;\n    fill-opacity:1;\n    fill-rule:nonzero;\n    stroke:none;\n    stroke-width:1px;\n    marker:none;\n    visibility:visible;\n    display:inline;\n    overflow:visible;\n    enable-background:accumulate\n}\n.wavedrom_svg_defs .s9 {\n    fill:#000;\n    fill-opacity:1;\n    stroke:none\n}\n.wavedrom_svg_defs .s10 {\n    color:#000;\n    fill:#fff;\n    fill-opacity:1;\n    fill-rule:nonzero;\n    stroke:none;\n    stroke-width:1px;\n    marker:none;\n    visibility:visible;\n    display:inline;\n    overflow:visible;\n    enable-background:accumulate\n}\n.wavedrom_svg_defs .s11 {\n    fill:#0041c4;\n    fill-opacity:1;\n    stroke:none\n}\n.wavedrom_svg_defs .s12 {\n    fill:none;\n    stroke:#0041c4;\n    stroke-width:1;\n    stroke-linecap:round;\n    stroke-linejoin:miter;\n    stroke-miterlimit:4;\n    stroke-opacity:1;\n    stroke-dasharray:none\n}\n\n/*wavedrom stop*/\n\n/* xsj patch start */\n\n.xiaoshujiang_code .code_line_break_hack{\n    margin:0;\n    border:0;\n    border-top:0;\n    border-bottom:0;\n}\n.component_attachment, .code_line_break_hack{\n  display: none;\n  visibility: collapse!important;\n  height: 0!important;\n}\n\n.blank_anchor_id {\n    float: right;\n    width: 1px\n}\n.blank_anchor_id {\n    visibility: hidden;\n}\n.blank_anchor_id:before {\n    content: 'a';\n}\n.xsj_foreignObject{\n  width: 100%!important;\n  height: 100%!important;\n}\n.xsj_foreignObject hr{\n    margin: inherit;\n}\n\n/* xsj patch end */\n\n","createDate":"October 10, 2018","updateDate":"October 10, 2018","tags":["标题编号","小书匠"],"cover":{"childImageSharp":{"fluid":{"tracedSVG":"data:image/svg+xml,%3csvg xmlns='http://www.w3.org/2000/svg' width='400' height='300'%3e%3cpath d='M337 5c0 6 0 7 6 19l6 14-21 4-21 4-10 21c-13 27-13 27-29 36-13 7-14 8-28 24-4 4-6 5-22 11l-17 7-2 12c-3 11-3 13-8 19l-6 6-1 1-2 5-2 3-15-4-15-3-7 19-7 18-10 5-22 16-11 10-14-1-15-1-8 16-7 15-3-4-9-16-7-11 1 11v14l1 4H20l-16 1H0v20h200l200-1V0h-28c-22 0-28 0-27 1h-1c-3-3-3-1 0 3l3 3v1c1 1 1 2-1 2-1 1-1 1 0 0l-1-1h-3l-1-1h-1v1l-1 1-1-5-1-5v5' fill='%23d3d3d3' fill-rule='evenodd'/%3e%3c/svg%3e","aspectRatio":1.3333333333333333,"src":"/roadbike/static/76ba2693b9a28edf93ce23c37e9313dc/e9c7b/cover.png","srcSet":"/roadbike/static/76ba2693b9a28edf93ce23c37e9313dc/69781/cover.png 250w,\n/roadbike/static/76ba2693b9a28edf93ce23c37e9313dc/3fa08/cover.png 500w,\n/roadbike/static/76ba2693b9a28edf93ce23c37e9313dc/e9c7b/cover.png 1000w,\n/roadbike/static/76ba2693b9a28edf93ce23c37e9313dc/572fb/cover.png 1024w","sizes":"(max-width: 1000px) 100vw, 1000px","originalImg":"/roadbike/static/76ba2693b9a28edf93ce23c37e9313dc/572fb/cover.png"}}},"meta":{"title":"2018-10-10 正文标题编号","tags":"标题编号,小书匠"}}},"pageContext":{"isCreatedByStatefulCreatePages":false,"slug":"numbered_heading","zipPath":"/home/suziwen/suziwengit/story/dillinger/roadbike/src/xsjposts/blogs/2018-10-10 正文标题编号.zip","pdfPath":"/home/suziwen/suziwengit/story/dillinger/roadbike/src/xsjposts/blogs/2018-10-10 正文标题编号.pdf","sidebarItems":[{"title":"概述","link":"/blog/numbered_heading#e6a682e8bfb0_1","items":[{"title":"正文标题编号的几种实现方式","link":"/blog/numbered_heading#e6ada3e69687e6a087e9a298e7bc96e58fb7e79a84e587a0e7a78de5ae9ee78eb0e696b9e5bc8f_2","hash":"e6ada3e69687e6a087e9a298e7bc96e58fb7e79a84e587a0e7a78de5ae9ee78eb0e696b9e5bc8f_2","parentUid":"概述","uid":"概述___正文标题编号的几种实现方式"}],"hash":"e6a682e8bfb0_1","parentUid":"","uid":"概述","key":"blog"},{"title":"样式法章节标题编号","link":"/blog/numbered_heading#e6a0b7e5bc8fe6b395e7aba0e88a82e6a087e9a298e7bc96e58fb7_3","items":[{"title":"实现方法","link":"/blog/numbered_heading#e5ae9ee78eb0e696b9e6b395_4","hash":"e5ae9ee78eb0e696b9e6b395_4","parentUid":"样式法章节标题编号","uid":"样式法章节标题编号___实现方法"},{"title":"优缺点","link":"/blog/numbered_heading#e4bc98e7bcbae782b9_5","items":[{"title":"优点","link":"/blog/numbered_heading#e4bc98e782b9_6","hash":"e4bc98e782b9_6","parentUid":"样式法章节标题编号___优缺点","uid":"样式法章节标题编号___优缺点___优点"},{"title":"缺点","link":"/blog/numbered_heading#e7bcbae782b9_7","hash":"e7bcbae782b9_7","parentUid":"样式法章节标题编号___优缺点","uid":"样式法章节标题编号___优缺点___缺点"}],"hash":"e4bc98e7bcbae782b9_5","parentUid":"样式法章节标题编号","uid":"样式法章节标题编号___优缺点"}],"hash":"e6a0b7e5bc8fe6b395e7aba0e88a82e6a087e9a298e7bc96e58fb7_3","parentUid":"","uid":"样式法章节标题编号","key":"blog"},{"title":"手写法章节标题编号","link":"/blog/numbered_heading#e6898be58699e6b395e7aba0e88a82e6a087e9a298e7bc96e58fb7_8","items":[{"title":"实现方法","link":"/blog/numbered_heading#e5ae9ee78eb0e696b9e6b395_9","hash":"e5ae9ee78eb0e696b9e6b395_9","parentUid":"手写法章节标题编号","uid":"手写法章节标题编号___实现方法"},{"title":"优缺点","link":"/blog/numbered_heading#e4bc98e7bcbae782b9_10","items":[{"title":"优点","link":"/blog/numbered_heading#e4bc98e782b9_11","hash":"e4bc98e782b9_11","parentUid":"手写法章节标题编号___优缺点","uid":"手写法章节标题编号___优缺点___优点"},{"title":"缺点","link":"/blog/numbered_heading#e7bcbae782b9_12","hash":"e7bcbae782b9_12","parentUid":"手写法章节标题编号___优缺点","uid":"手写法章节标题编号___优缺点___缺点"}],"hash":"e4bc98e7bcbae782b9_10","parentUid":"手写法章节标题编号","uid":"手写法章节标题编号___优缺点"}],"hash":"e6898be58699e6b395e7aba0e88a82e6a087e9a298e7bc96e58fb7_8","parentUid":"","uid":"手写法章节标题编号","key":"blog"},{"title":"解析法章节标题编号","link":"/blog/numbered_heading#e8a7a3e69e90e6b395e7aba0e88a82e6a087e9a298e7bc96e58fb7_13","items":[{"title":"实现原理","link":"/blog/numbered_heading#e5ae9ee78eb0e58e9fe79086_14","hash":"e5ae9ee78eb0e58e9fe79086_14","parentUid":"解析法章节标题编号","uid":"解析法章节标题编号___实现原理"},{"title":"开启方法","link":"/blog/numbered_heading#e5bc80e590afe696b9e6b395_15","hash":"e5bc80e590afe696b9e6b395_15","parentUid":"解析法章节标题编号","uid":"解析法章节标题编号___开启方法"},{"title":"配置说明","link":"/blog/numbered_heading#e9858de7bdaee8afb4e6988e_16","items":[{"title":"如何修改标题编号规则","link":"/blog/numbered_heading#e5a682e4bd95e4bfaee694b9e6a087e9a298e7bc96e58fb7e8a784e58899_17","items":[{"title":"支持的编号显示格式","link":"/blog/numbered_heading#e694afe68c81e79a84e7bc96e58fb7e698bee7a4bae6a0bce5bc8f_18","hash":"e694afe68c81e79a84e7bc96e58fb7e698bee7a4bae6a0bce5bc8f_18","parentUid":"解析法章节标题编号___配置说明___如何修改标题编号规则","uid":"解析法章节标题编号___配置说明___如何修改标题编号规则___支持的编号显示格式"}],"hash":"e5a682e4bd95e4bfaee694b9e6a087e9a298e7bc96e58fb7e8a784e58899_17","parentUid":"解析法章节标题编号___配置说明","uid":"解析法章节标题编号___配置说明___如何修改标题编号规则"},{"title":"编号计算规则","link":"/blog/numbered_heading#e7bc96e58fb7e8aea1e7ae97e8a784e58899_19","hash":"e7bc96e58fb7e8aea1e7ae97e8a784e58899_19","parentUid":"解析法章节标题编号___配置说明","uid":"解析法章节标题编号___配置说明___编号计算规则"},{"title":"元数据","link":"/blog/numbered_heading#e58583e695b0e68dae_20","hash":"e58583e695b0e68dae_20","parentUid":"解析法章节标题编号___配置说明","uid":"解析法章节标题编号___配置说明___元数据"}],"hash":"e9858de7bdaee8afb4e6988e_16","parentUid":"解析法章节标题编号","uid":"解析法章节标题编号___配置说明"},{"title":"优缺点","link":"/blog/numbered_heading#e4bc98e7bcbae782b9_21","items":[{"title":"优点","link":"/blog/numbered_heading#e4bc98e782b9_22","hash":"e4bc98e782b9_22","parentUid":"解析法章节标题编号___优缺点","uid":"解析法章节标题编号___优缺点___优点"},{"title":"缺点","link":"/blog/numbered_heading#e7bcbae782b9_23","hash":"e7bcbae782b9_23","parentUid":"解析法章节标题编号___优缺点","uid":"解析法章节标题编号___优缺点___缺点"}],"hash":"e4bc98e7bcbae782b9_21","parentUid":"解析法章节标题编号","uid":"解析法章节标题编号___优缺点"}],"hash":"e8a7a3e69e90e6b395e7aba0e88a82e6a087e9a298e7bc96e58fb7_13","parentUid":"","uid":"解析法章节标题编号","key":"blog"},{"title":"其他","link":"/blog/numbered_heading#e585b6e4bb96_24","hash":"e585b6e4bb96_24","parentUid":"","uid":"其他","key":"blog"}],"enableScrollSync":true,"prev":{"title":"2018-4-25 自定义 css 样式调整块级图片标题显示位置","toc":"[{\"title\":\"概述\",\"link\":\"modify_image_title_by_custom_css#e6a682e8bfb0_1\"},{\"title\":\"自定义-css-样式调整标题位置\",\"link\":\"modify_image_title_by_custom_css#e887aae5ae9ae4b98920css20e6a0b7e5bc8fe8b083e695b4e6a087e9a298e4bd8de7bdae_2\",\"items\":[{\"title\":\"几个调整位置的示例\",\"link\":\"modify_image_title_by_custom_css#e587a0e4b8aae8b083e695b4e4bd8de7bdaee79a84e7a4bae4be8b_3\",\"items\":[{\"title\":\"将标题置于图片外的上方居中\",\"link\":\"modify_image_title_by_custom_css#e5b086e6a087e9a298e7bdaee4ba8ee59bbee78987e5a496e79a84e4b88ae696b9e5b185e4b8ad_4\"},{\"title\":\"将标题置于图片外的右上方\",\"link\":\"modify_image_title_by_custom_css#e5b086e6a087e9a298e7bdaee4ba8ee59bbee78987e5a496e79a84e58fb3e4b88ae696b9_5\"},{\"title\":\"将标题置于图片外的左上方\",\"link\":\"modify_image_title_by_custom_css#e5b086e6a087e9a298e7bdaee4ba8ee59bbee78987e5a496e79a84e5b7a6e4b88ae696b9_6\"},{\"title\":\"将标题置于图片外的左下方\",\"link\":\"modify_image_title_by_custom_css#e5b086e6a087e9a298e7bdaee4ba8ee59bbee78987e5a496e79a84e5b7a6e4b88be696b9_7\"},{\"title\":\"将标题置于图片外的右下方\",\"link\":\"modify_image_title_by_custom_css#e5b086e6a087e9a298e7bdaee4ba8ee59bbee78987e5a496e79a84e58fb3e4b88be696b9_8\"},{\"title\":\"将标题置于图片内的上方居中\",\"link\":\"modify_image_title_by_custom_css#e5b086e6a087e9a298e7bdaee4ba8ee59bbee78987e58685e79a84e4b88ae696b9e5b185e4b8ad_9\"},{\"title\":\"将标题置于图片内的右上方\",\"link\":\"modify_image_title_by_custom_css#e5b086e6a087e9a298e7bdaee4ba8ee59bbee78987e58685e79a84e58fb3e4b88ae696b9_10\"},{\"title\":\"将标题置于图片内的左上方\",\"link\":\"modify_image_title_by_custom_css#e5b086e6a087e9a298e7bdaee4ba8ee59bbee78987e58685e79a84e5b7a6e4b88ae696b9_11\"},{\"title\":\"将标题置于图片内的左下方\",\"link\":\"modify_image_title_by_custom_css#e5b086e6a087e9a298e7bdaee4ba8ee59bbee78987e58685e79a84e5b7a6e4b88be696b9_12\"},{\"title\":\"将标题置于图片内的右下方\",\"link\":\"modify_image_title_by_custom_css#e5b086e6a087e9a298e7bdaee4ba8ee59bbee78987e58685e79a84e58fb3e4b88be696b9_13\"},{\"title\":\"将标题置于图片内的下方居中\",\"link\":\"modify_image_title_by_custom_css#e5b086e6a087e9a298e7bdaee4ba8ee59bbee78987e58685e79a84e4b88be696b9e5b185e4b8ad_14\"}]}]}]","docType":"blogs","slug":"modify_image_title_by_custom_css","zipPath":"/home/suziwen/suziwengit/story/dillinger/roadbike/src/xsjposts/blogs/2018-4-25 自定义 css 样式调整块级图片标题显示位置.zip","tags":["教程"," 样式","小书匠"],"updateDate":"2018-04-24T16:00:00.000Z","excerpt":"从小书匠 5.7.6 版本开始，小书匠对块级图片生成的 html 结构进行了调整。 将原来的 story_image_caption 放到了 story_image 标签内。通过该修改后，用户可以通过自定义 css 样式时，比较方便的进行标题位置的调整。\n通过自定义 css 样式..."},"next":{"title":"小书匠付费流程","toc":"[{\"title\":\"首次付费流程\",\"link\":\"vip/price/flow#e9a696e6aca1e4bb98e8b4b9e6b581e7a88b_1\"},{\"title\":\"继费流程\",\"link\":\"vip/price/flow#e7bba7e8b4b9e6b581e7a88b_2\"},{\"title\":\"付费常见问题\",\"link\":\"vip/price/flow#e4bb98e8b4b9e5b8b8e8a781e997aee9a298_3\",\"items\":[{\"title\":\"临时会员和正式会员有什么差别\",\"link\":\"vip/price/flow#e4b8b4e697b6e4bc9ae59198e5928ce6ada3e5bc8fe4bc9ae59198e69c89e4bb80e4b988e5b7aee588ab_4\"},{\"title\":\"为什么要设置临时会员\",\"link\":\"vip/price/flow#e4b8bae4bb80e4b988e8a681e8aebee7bdaee4b8b4e697b6e4bc9ae59198_5\"},{\"title\":\"为什么不支持到账后自动升级会员\",\"link\":\"vip/price/flow#e4b8bae4bb80e4b988e4b88de694afe68c81e588b0e8b4a6e5908ee887aae58aa8e58d87e7baa7e4bc9ae59198_6\"},{\"title\":\"付完款后一般多长时间能正式升级为正式会员\",\"link\":\"vip/price/flow#e4bb98e5ae8ce6acbee5908ee4b880e888ace5a49ae995bfe697b6e997b4e883bde6ada3e5bc8fe58d87e7baa7e4b8bae6ada3e5bc8fe4bc9ae59198_7\"},{\"title\":\"为什么付款这么麻烦\",\"link\":\"vip/price/flow#e4b8bae4bb80e4b988e4bb98e6acbee8bf99e4b988e9babbe783a6_8\"},{\"title\":\"我付款了但是我忘记了写备注怎么办\",\"link\":\"vip/price/flow#e68891e4bb98e6acbee4ba86efbc8ce4bd86e698afe68891e5bf98e8aeb0e4ba86e58699e5a487e6b3a8efbc8ce6808ee4b988e58a9ee38082_9\"},{\"title\":\"我付款太多怎么申请退回多付的金额\",\"link\":\"vip/price/flow#e68891e4bb98e6acbee5a4aae5a49aefbc8ce6808ee4b988e794b3e8afb7e98080e59b9ee5a49ae4bb98e79a84e98791e9a29d_10\"}]}]","docType":"blogs","slug":"vip/price/flow","zipPath":"/home/suziwen/suziwengit/story/dillinger/roadbike/src/xsjposts/blogs/小书匠付费流程.zip","tags":["小书匠","付费流程"],"updateDate":"2019-01-16T06:47:48.993Z","excerpt":"注： 蓝色背景的是需要用户操作的地方\n临时会员除了无法在线升级，其他功能跟正式会员一样\n因为小书匠还没办法做到用户付款后，立即开通会员功能，需要经过管理员人工确认后，才能正式升级为会员。这段过程大概需要1到10天的时间，受很多外在因素影响。因此提供了一个临时会员功能，用户在付完款..."},"related":[{"node":{"title":"小书匠语法说明之脚注","toc":"[{\"title\":\"概述\",\"link\":\"grammar/advance/footnote#e6a682e8bfb0_1\"},{\"title\":\"使用\",\"link\":\"grammar/advance/footnote#e4bdbfe794a8_2\",\"items\":[{\"title\":\"内联式脚注\",\"link\":\"grammar/advance/footnote#e58685e88194e5bc8fe8849ae6b3a8_3\",\"items\":[{\"title\":\"示例\",\"link\":\"grammar/advance/footnote#e7a4bae4be8b_4\"},{\"title\":\"效果\",\"link\":\"grammar/advance/footnote#e69588e69e9c_5\"}]},{\"title\":\"引用式脚注\",\"link\":\"grammar/advance/footnote#e5bc95e794a8e5bc8fe8849ae6b3a8_6\",\"items\":[{\"title\":\"示例\",\"link\":\"grammar/advance/footnote#e7a4bae4be8b_7\"},{\"title\":\"效果\",\"link\":\"grammar/advance/footnote#e69588e69e9c_8\"}]},{\"title\":\"html\",\"link\":\"grammar/advance/footnote#html_9\"},{\"title\":\"多行脚注内容\",\"link\":\"grammar/advance/footnote#e5a49ae8a18ce8849ae6b3a8e58685e5aeb9_10\",\"items\":[{\"title\":\"示例\",\"link\":\"grammar/advance/footnote#e7a4bae4be8b_11\"},{\"title\":\"效果\",\"link\":\"grammar/advance/footnote#e69588e69e9c_12\"}]},{\"title\":\"重复脚注引用\",\"link\":\"grammar/advance/footnote#e9878de5a48de8849ae6b3a8e5bc95e794a8_13\",\"items\":[{\"title\":\"示例\",\"link\":\"grammar/advance/footnote#e7a4bae4be8b_14\"},{\"title\":\"效果\",\"link\":\"grammar/advance/footnote#e69588e69e9c_15\"}]}]},{\"title\":\"疑问\",\"link\":\"grammar/advance/footnote#e79691e997ae_16\"},{\"title\":\"相关\",\"link\":\"grammar/advance/footnote#e79bb8e585b3_17\"}]","docType":"docs","slug":"grammar/advance/footnote","zipPath":"/home/suziwen/suziwengit/story/dillinger/roadbike/src/xsjposts/docs/语法/小书匠语法说明之脚注.zip","tags":["markdown"," 语法","脚注","小书匠"],"updateDate":"2019-01-02T01:51:00.739Z","excerpt":"脚注语法不是标准的 commonmark，  不同的编辑器或者博客平台支持可能不一样。小书匠使用 markdown-it 的扩展 markdown-it-footnote 实现对上标的支持。\n元数据标识: grammar_footnote\n想要使用该语法，需要在设置&gt;扩展语..."}},{"node":{"title":"6.7.0 升级日志","toc":"[{\"title\":\"670\",\"link\":\"version/v_6_7_0#670_1\",\"items\":[{\"title\":\"新功能\",\"link\":\"version/v_6_7_0#e696b0e58a9fe883bd_2\"},{\"title\":\"修改\",\"link\":\"version/v_6_7_0#e4bfaee694b9_3\"}]}]","docType":"logs","slug":"version/v_6_7_0","zipPath":"/home/suziwen/suziwengit/story/dillinger/roadbike/src/xsjposts/logs/6.7.0 升级日志.zip","tags":["升级","日志","小书匠"],"updateDate":"2018-11-01T00:00:00.000Z","excerpt":""}},{"node":{"title":"小书匠语法说明之分隔线","toc":"[{\"title\":\"概述\",\"link\":\"grammar/common/horizontal#e6a682e8bfb0_1\"},{\"title\":\"使用\",\"link\":\"grammar/common/horizontal#e4bdbfe794a8_2\",\"items\":[{\"title\":\"示例\",\"link\":\"grammar/common/horizontal#e7a4bae4be8b_3\"},{\"title\":\"html\",\"link\":\"grammar/common/horizontal#html_4\"},{\"title\":\"效果\",\"link\":\"grammar/common/horizontal#e69588e69e9c_5\"}]},{\"title\":\"扩展\",\"link\":\"grammar/common/horizontal#e689a9e5b195_6\",\"items\":[{\"title\":\"pdf-打印强制分页\",\"link\":\"grammar/common/horizontal#pdf20e68993e58db0e5bcbae588b6e58886e9a1b5_7\",\"items\":[{\"title\":\"使用\",\"link\":\"grammar/common/horizontal#e4bdbfe794a8_8\"},{\"title\":\"原理\",\"link\":\"grammar/common/horizontal#e58e9fe79086_9\"}]},{\"title\":\"ppt-分页\",\"link\":\"grammar/common/horizontal#ppt20e58886e9a1b5_10\"}]},{\"title\":\"疑问\",\"link\":\"grammar/common/horizontal#e79691e997ae_11\"},{\"title\":\"相关\",\"link\":\"grammar/common/horizontal#e79bb8e585b3_12\"}]","docType":"docs","slug":"grammar/common/horizontal","zipPath":"/home/suziwen/suziwengit/story/dillinger/roadbike/src/xsjposts/docs/语法/小书匠语法说明之分隔线.zip","tags":["markdown"," 语法","基础语法"," 分隔线","小书匠"],"updateDate":"2018-12-27T08:00:57.546Z","excerpt":"分隔线用来在文章内插入一条水平线，显性分隔段落间的文字。对于 pdf 打印，用户可以通过自定义 css 样式，来实现分隔线分页效果。\n在一行内，包含三个 (以上)-, * 或者_ 相同符号，就可以产生一个分隔线效果。需要注意的是连继三个 - 符号的上一行如果有文字，就会生产章节二..."}},{"node":{"title":"小书匠语法说明之表格","toc":"[{\"title\":\"概述\",\"link\":\"grammar/advance/table#e6a682e8bfb0_1\"},{\"title\":\"普通表格\",\"link\":\"grammar/advance/table#e699aee9809ae8a1a8e6a0bc_2\",\"items\":[{\"title\":\"常规用法\",\"link\":\"grammar/advance/table#e5b8b8e8a784e794a8e6b395_3\",\"items\":[{\"title\":\"示例\",\"link\":\"grammar/advance/table#e7a4bae4be8b_4\"},{\"title\":\"效果\",\"link\":\"grammar/advance/table#e69588e69e9c_5\"}]},{\"title\":\"表格内容对齐\",\"link\":\"grammar/advance/table#e8a1a8e6a0bce58685e5aeb9e5afb9e9bd90_6\",\"items\":[{\"title\":\"示例\",\"link\":\"grammar/advance/table#e7a4bae4be8b_7\"},{\"title\":\"效果\",\"link\":\"grammar/advance/table#e69588e69e9c_8\"}]}]},{\"title\":\"增强型表格\",\"link\":\"grammar/advance/table#e5a29ee5bcbae59e8be8a1a8e6a0bc_9\",\"items\":[{\"title\":\"如何打开增强型表格语法功能\",\"link\":\"grammar/advance/table#e5a682e4bd95e68993e5bc80e5a29ee5bcbae59e8be8a1a8e6a0bce8afade6b395e58a9fe883bd_10\"},{\"title\":\"行单元格合并\",\"link\":\"grammar/advance/table#e8a18ce58d95e58583e6a0bce59088e5b9b6_11\",\"items\":[{\"title\":\"示例\",\"link\":\"grammar/advance/table#e7a4bae4be8b_12\"},{\"title\":\"效果\",\"link\":\"grammar/advance/table#e69588e69e9c_13\"},{\"title\":\"html\",\"link\":\"grammar/advance/table#html_14\"}]},{\"title\":\"列单元格合并\",\"link\":\"grammar/advance/table#e58897e58d95e58583e6a0bce59088e5b9b6_15\",\"items\":[{\"title\":\"示例\",\"link\":\"grammar/advance/table#e7a4bae4be8b_16\"},{\"title\":\"效果\",\"link\":\"grammar/advance/table#e69588e69e9c_17\"},{\"title\":\"html\",\"link\":\"grammar/advance/table#html_18\"}]},{\"title\":\"表格标题\",\"link\":\"grammar/advance/table#e8a1a8e6a0bce6a087e9a298_19\",\"items\":[{\"title\":\"示例\",\"link\":\"grammar/advance/table#e7a4bae4be8b_20\"},{\"title\":\"效果\",\"link\":\"grammar/advance/table#e69588e69e9c_21\"},{\"title\":\"html\",\"link\":\"grammar/advance/table#html_22\"}]},{\"title\":\"多表格头\",\"link\":\"grammar/advance/table#e5a49ae8a1a8e6a0bce5a4b4_23\",\"items\":[{\"title\":\"示例\",\"link\":\"grammar/advance/table#e7a4bae4be8b_24\"},{\"title\":\"效果\",\"link\":\"grammar/advance/table#e69588e69e9c_25\"},{\"title\":\"html\",\"link\":\"grammar/advance/table#html_26\"}]},{\"title\":\"多表格身\",\"link\":\"grammar/advance/table#e5a49ae8a1a8e6a0bce8baab_27\",\"items\":[{\"title\":\"示例\",\"link\":\"grammar/advance/table#e7a4bae4be8b_28\"},{\"title\":\"效果\",\"link\":\"grammar/advance/table#e69588e69e9c_29\"},{\"title\":\"html\",\"link\":\"grammar/advance/table#html_30\"}]},{\"title\":\"一个比较复杂的表格例子\",\"link\":\"grammar/advance/table#e4b880e4b8aae6af94e8be83e5a48de69d82e79a84e8a1a8e6a0bce4be8be5ad90_31\",\"items\":[{\"title\":\"示例\",\"link\":\"grammar/advance/table#e7a4bae4be8b_32\"},{\"title\":\"效果\",\"link\":\"grammar/advance/table#e69588e69e9c_33\"}]}]},{\"title\":\"疑问\",\"link\":\"grammar/advance/table#e79691e997ae_34\"},{\"title\":\"相关\",\"link\":\"grammar/advance/table#e79bb8e585b3_35\"}]","docType":"docs","slug":"grammar/advance/table","zipPath":"/home/suziwen/suziwengit/story/dillinger/roadbike/src/xsjposts/docs/语法/小书匠语法说明之表格.zip","tags":["markdown"," 语法","表格","小书匠"],"updateDate":"2019-01-02T01:50:52.710Z","excerpt":"小书匠除了支持基础的表格语法外，还对表格功能进行能增强，比如行合并单元格，列合并单元格，多表格头，多表格身等\n单元格左对齐\n左对齐\n右对齐\n居中对齐\n元数据 : grammar_tableExtra\n如果单元格的右侧内容为空时，系统自动向右合并单元格。\n系统也支持在前一个单元格输..."}},{"node":{"title":"小书匠数据中心使用说明","toc":"[{\"title\":\"概述\",\"link\":\"tutorial/database#e6a682e8bfb0_1\",\"items\":[{\"title\":\"couch-协议\",\"link\":\"tutorial/database#couch20e58d8fe8aeae_2\"},{\"title\":\"pouchdb\",\"link\":\"tutorial/database#pouchdb_3\"},{\"title\":\"couchdb\",\"link\":\"tutorial/database#couchdb_4\"},{\"title\":\"数据库和第三方存储的差别\",\"link\":\"tutorial/database#e695b0e68daee5ba93e5928ce7acace4b889e696b9e5ad98e582a8e79a84e5b7aee588ab_5\"},{\"title\":\"为什么不把第三方存储也做成实时保存\",\"link\":\"tutorial/database#e4b8bae4bb80e4b988e4b88de68a8ae7acace4b889e696b9e5ad98e582a8e4b99fe5819ae68890e5ae9ee697b6e4bf9de5ad98_6\"}]},{\"title\":\"本地数据库管理\",\"link\":\"tutorial/database#e69cace59cb0e695b0e68daee5ba93e7aea1e79086_7\",\"items\":[{\"title\":\"重置数据库\",\"link\":\"tutorial/database#e9878de7bdaee695b0e68daee5ba93_8\"},{\"title\":\"压缩数据库\",\"link\":\"tutorial/database#e58e8be7bca9e695b0e68daee5ba93_9\"},{\"title\":\"删除数据库\",\"link\":\"tutorial/database#e588a0e999a4e695b0e68daee5ba93_10\"}]},{\"title\":\"远程数据库\",\"link\":\"tutorial/database#e8bf9ce7a88be695b0e68daee5ba93_11\",\"items\":[{\"title\":\"小书匠临时数据库\",\"link\":\"tutorial/database#e5b08fe4b9a6e58ca0e4b8b4e697b6e695b0e68daee5ba93_12\"},{\"title\":\"自定义远程数据库\",\"link\":\"tutorial/database#e887aae5ae9ae4b989e8bf9ce7a88be695b0e68daee5ba93_13\"},{\"title\":\"数据同步\",\"link\":\"tutorial/database#e695b0e68daee5908ce6ada5_14\",\"items\":[{\"title\":\"实时同步\",\"link\":\"tutorial/database#e5ae9ee697b6e5908ce6ada5_15\"},{\"title\":\"手动同步\",\"link\":\"tutorial/database#e6898be58aa8e5908ce6ada5_16\",\"items\":[{\"title\":\"双向同步\",\"link\":\"tutorial/database#e58f8ce59091e5908ce6ada5_17\"},{\"title\":\"拉取\",\"link\":\"tutorial/database#e68b89e58f96_18\"},{\"title\":\"推送\",\"link\":\"tutorial/database#e68ea8e98081_19\"}]}]}]},{\"title\":\"相关\",\"link\":\"tutorial/database#e79bb8e585b3_20\"}]","docType":"docs","slug":"tutorial/database","zipPath":"/home/suziwen/suziwengit/story/dillinger/roadbike/src/xsjposts/docs/教程/小书匠数据中心使用说明.zip","tags":["数据中心","教程","小书匠"],"updateDate":"2019-01-15T04:59:32.987Z","excerpt":"小书匠内置数据库使用了 PouchDB ,一款非关系型数据库 NOSQL，非常适合文档数据的存储，又比一般的 NOSQL 数据库，比如 MONOGO ，多提供了数据同步和历史记录功能。\n小书匠提出了数据中心的概念，用来帮助用户通过底层数据的形式更加容易的维护自己的数据安全。目前免..."}},{"node":{"title":"印象笔记标签树显示功能","toc":"[{\"title\":\"概述\",\"link\":\"evernote/tags_support#e6a682e8bfb0_1\",\"items\":[{\"title\":\"标签树\",\"link\":\"evernote/tags_support#e6a087e7adbee6a091_2\",\"items\":[{\"title\":\"标签树过滤\",\"link\":\"evernote/tags_support#e6a087e7adbee6a091e8bf87e6bba4_3\"},{\"title\":\"标签树刷新\",\"link\":\"evernote/tags_support#e6a087e7adbee6a091e588b7e696b0_4\"}]},{\"title\":\"单标签显示文件列表\",\"link\":\"evernote/tags_support#e58d95e6a087e7adbee698bee7a4bae69687e4bbb6e58897e8a1a8_5\"},{\"title\":\"多标签组合显示文件列表\",\"link\":\"evernote/tags_support#e5a49ae6a087e7adbee7bb84e59088e698bee7a4bae69687e4bbb6e58897e8a1a8_6\"},{\"title\":\"标签文件列表\",\"link\":\"evernote/tags_support#e6a087e7adbee69687e4bbb6e58897e8a1a8_7\"}]}]","docType":"blogs","slug":"evernote/tags_support","zipPath":"/home/suziwen/suziwengit/story/dillinger/roadbike/src/xsjposts/blogs/印象笔记标签树显示功能.zip","tags":["印象笔记","标签","小书匠"],"updateDate":"2019-02-12T16:00:00.000Z","excerpt":"小书匠从 7.0.0 版本开始，支持对印象笔记的标签树形式显示文件功能。用户可以基于标签来管理自己在印象笔记上的文章。\n注: 该功能仅对会员开放，非会员在进行列表显示时，只会列出前5篇文章。 \n\n\n如果用户的标签比较多，可以通过该过滤功能，显示相关标签。 \n当第一次进入标签树主界面时..."}}]}}